[
  {
    "file_name": "BzGYe-8r---gOxJB.mp4",
    "user": {
      "screen_name": "kaka_lac",
      "name": "kaka"
    },
    "media_type": "videos",
    "url": "https://video.twimg.com/amplify_video/2056042775372828672/vid/avc1/720x1280/BzGYe-8r---gOxJB.mp4?tag=27",
    "read_time": "2026-05-18T01:01:54",
    "is_uploaded": true,
    "upload_info": {
      "success": true,
      "message_id": 24067,
      "timestamp": "2026-05-18T01:01:59"
    },
    "is_downloaded": true,
    "download_info": {
      "success": true,
      "size": 1942618,
      "size_mb": 1.85,
      "timestamp": "2026-05-18T01:01:56",
      "download_attempts": 0
    },
    "full_text": "https://t.co/0gQF4oafEb（可以支付宝付款订阅）\nhttps://t.co/MmbJNJD3Ui\ntelegram永久会员群，同步更新（一次交费，永久会员） https://t.co/tGQRvxo2o5",
    "publish_time": "2026-05-18T00:03:07"
  },
  {
    "file_name": "HIiJLh2b0AAYQjI.jpg",
    "user": {
      "screen_name": "Doraemonphoto",
      "name": "Doraemon"
    },
    "media_type": "images",
    "url": "https://pbs.twimg.com/media/HIiJLh2b0AAYQjI.jpg",
    "read_time": "2026-05-18T01:01:54",
    "is_uploaded": true,
    "upload_info": {
      "success": true,
      "message_id": 24068,
      "timestamp": "2026-05-18T01:02:00"
    },
    "is_downloaded": true,
    "download_info": {
      "success": true,
      "size": 116445,
      "size_mb": 0.11,
      "timestamp": "2026-05-18T01:02:00",
      "download_attempts": 0
    },
    "full_text": "gooner🧠 https://t.co/NaXrCfGX1Z",
    "publish_time": "2026-05-18T00:08:03"
  },
  {
    "file_name": "alUOrWzdM5XQxjPq.mp4",
    "user": {
      "screen_name": "sx84604818",
      "name": "Rexsonic Man+ suits & socks"
    },
    "media_type": "videos",
    "url": "https://video.twimg.com/amplify_video/2056049758561808385/vid/avc1/720x1280/alUOrWzdM5XQxjPq.mp4?tag=27",
    "read_time": "2026-05-18T01:01:54",
    "is_uploaded": true,
    "upload_info": {
      "success": true,
      "message_id": 24069,
      "timestamp": "2026-05-18T01:02:03"
    },
    "is_downloaded": true,
    "download_info": {
      "success": true,
      "size": 1591125,
      "size_mb": 1.52,
      "timestamp": "2026-05-18T01:02:01",
      "download_attempts": 0
    },
    "full_text": "👔西裝愛好者👔 https://t.co/J7Su75feRz",
    "publish_time": "2026-05-18T00:32:40"
  },
  {
    "file_name": "nYwhWGPFJiKF_83Q.mp4",
    "user": {
      "screen_name": "Azrael64300",
      "name": "薅壕好昊"
    },
    "media_type": "videos",
    "url": "https://video.twimg.com/ext_tw_video/1881024902465245184/pu/vid/avc1/1280x720/nYwhWGPFJiKF_83Q.mp4?tag=12",
    "read_time": "2026-05-18T01:01:54",
    "is_uploaded": true,
    "upload_info": {
      "success": true,
      "message_id": 24070,
      "timestamp": "2026-05-18T01:02:08"
    },
    "is_downloaded": true,
    "download_info": {
      "success": true,
      "size": 23030338,
      "size_mb": 21.96,
      "timestamp": "2026-05-18T01:02:05",
      "download_attempts": 0
    },
    "full_text": "https://t.co/sOV8uhYKWa",
    "publish_time": "2026-05-18T00:48:20"
  },
  {
    "file_name": "k_eiuahX8TkWiZfC.mp4",
    "user": {
      "screen_name": "sx84604818",
      "name": "Rexsonic Man+ suits & socks"
    },
    "media_type": "videos",
    "url": "https://video.twimg.com/amplify_video/2056054320177836032/vid/avc1/720x398/k_eiuahX8TkWiZfC.mp4?tag=27",
    "read_time": "2026-05-18T01:01:54",
    "is_uploaded": true,
    "upload_info": {
      "success": true,
      "message_id": 24071,
      "timestamp": "2026-05-18T01:02:10"
    },
    "is_downloaded": true,
    "download_info": {
      "success": true,
      "size": 664429,
      "size_mb": 0.63,
      "timestamp": "2026-05-18T01:02:09",
      "download_attempts": 0
    },
    "full_text": "👔西裝愛好者👔 https://t.co/qebwwRSelS",
    "publish_time": "2026-05-18T00:49:21"
  },
  {
    "file_name": "CKqVhNlBYj43pip4.mp4",
    "user": {
      "screen_name": "77baxi",
      "name": "健身教练cd伪娘"
    },
    "media_type": "videos",
    "url": "https://video.twimg.com/amplify_video/2055816480990855168/vid/avc1/1280x720/CKqVhNlBYj43pip4.mp4?tag=27",
    "read_time": "2026-05-18T02:02:48",
    "is_uploaded": true,
    "upload_info": {
      "success": true,
      "message_id": 24073,
      "timestamp": "2026-05-18T02:02:55"
    },
    "is_downloaded": true,
    "download_info": {
      "success": true,
      "size": 11902417,
      "size_mb": 11.35,
      "timestamp": "2026-05-18T02:02:51",
      "download_attempts": 0
    },
    "full_text": "https://t.co/1qmZ4SoqZt",
    "publish_time": "2026-05-18T01:44:35"
  },
  {
    "file_name": "u-mM98AOFvo67KLE.mp4",
    "user": {
      "screen_name": "arthurz_xcx",
      "name": "Arthur (อาเธอร์) ♠︎"
    },
    "media_type": "videos",
    "url": "https://video.twimg.com/amplify_video/2056070930825412608/vid/avc1/2160x3840/u-mM98AOFvo67KLE.mp4?tag=27",
    "read_time": "2026-05-18T02:02:48",
    "is_uploaded": false,
    "upload_info": {
      "success": false,
      "error_type": "file_too_large",
      "message": "videos大小超标 (54MB > 50MB)",
      "timestamp": "2026-05-18T02:03:00",
      "notification_sent": true
    },
    "is_downloaded": true,
    "download_info": {
      "success": true,
      "size": 57561250,
      "size_mb": 54.89,
      "timestamp": "2026-05-18T03:02:00",
      "download_attempts": 0
    },
    "full_text": "been edging for 2 hours now 🥵 https://t.co/6kI3JYJLw3",
    "publish_time": "2026-05-18T01:55:36"
  },
  {
    "file_name": "HIilSRYaQAA2GlA.jpg",
    "user": {
      "screen_name": "Alfred_yh_",
      "name": "机械臂Luk"
    },
    "media_type": "images",
    "url": "https://pbs.twimg.com/media/HIilSRYaQAA2GlA.jpg",
    "read_time": "2026-05-18T03:01:59",
    "is_uploaded": true,
    "upload_info": {
      "success": true,
      "message_id": 24074,
      "timestamp": "2026-05-18T03:02:03"
    },
    "is_downloaded": true,
    "download_info": {
      "success": true,
      "size": 199409,
      "size_mb": 0.19,
      "timestamp": "2026-05-18T03:02:01",
      "download_attempts": 0
    },
    "full_text": "请勿随意流水 https://t.co/DMmt4guPnA",
    "publish_time": "2026-05-18T02:10:49"
  },
  {
    "file_name": "HIilSRZbsAAAKy_.jpg",
    "user": {
      "screen_name": "Alfred_yh_",
      "name": "机械臂Luk"
    },
    "media_type": "images",
    "url": "https://pbs.twimg.com/media/HIilSRZbsAAAKy_.jpg",
    "read_time": "2026-05-18T03:01:59",
    "is_uploaded": true,
    "upload_info": {
      "success": true,
      "message_id": 24075,
      "timestamp": "2026-05-18T03:02:05"
    },
    "is_downloaded": true,
    "download_info": {
      "success": true,
      "size": 89209,
      "size_mb": 0.09,
      "timestamp": "2026-05-18T03:02:03",
      "download_attempts": 0
    },
    "full_text": "请勿随意流水 https://t.co/DMmt4guPnA",
    "publish_time": "2026-05-18T02:10:49"
  },
  {
    "file_name": "HIimDNra8AALUwx.jpg",
    "user": {
      "screen_name": "Uji_Hikaru",
      "name": "虎不理"
    },
    "media_type": "images",
    "url": "https://pbs.twimg.com/media/HIimDNra8AALUwx.jpg",
    "read_time": "2026-05-18T03:01:59",
    "is_uploaded": true,
    "upload_info": {
      "success": true,
      "message_id": 24076,
      "timestamp": "2026-05-18T03:02:06"
    },
    "is_downloaded": true,
    "download_info": {
      "success": true,
      "size": 145575,
      "size_mb": 0.14,
      "timestamp": "2026-05-18T03:02:05",
      "download_attempts": 0
    },
    "full_text": "https://t.co/oTS84oqMXx",
    "publish_time": "2026-05-18T02:14:22"
  },
  {
    "file_name": "HIimDNraQAARHko.jpg",
    "user": {
      "screen_name": "Uji_Hikaru",
      "name": "虎不理"
    },
    "media_type": "images",
    "url": "https://pbs.twimg.com/media/HIimDNraQAARHko.jpg",
    "read_time": "2026-05-18T03:01:59",
    "is_uploaded": true,
    "upload_info": {
      "success": true,
      "message_id": 24077,
      "timestamp": "2026-05-18T03:02:08"
    },
    "is_downloaded": true,
    "download_info": {
      "success": true,
      "size": 100225,
      "size_mb": 0.1,
      "timestamp": "2026-05-18T03:02:07",
      "download_attempts": 0
    },
    "full_text": "https://t.co/oTS84oqMXx",
    "publish_time": "2026-05-18T02:14:22"
  },
  {
    "file_name": "HIjJxdXbEAA04fB.jpg",
    "user": {
      "screen_name": "eric_kk97",
      "name": "ManFeed🍆"
    },
    "media_type": "images",
    "url": "https://pbs.twimg.com/media/HIjJxdXbEAA04fB.jpg",
    "read_time": "2026-05-18T05:01:58",
    "is_uploaded": true,
    "upload_info": {
      "success": true,
      "message_id": 24078,
      "timestamp": "2026-05-18T05:02:01"
    },
    "is_downloaded": true,
    "download_info": {
      "success": true,
      "size": 174585,
      "size_mb": 0.17,
      "timestamp": "2026-05-18T05:01:59",
      "download_attempts": 0
    },
    "full_text": "https://t.co/DslnHbN3Ns",
    "publish_time": "2026-05-18T04:50:12"
  },
  {
    "file_name": "HIjRfMFaMAE4z9s.jpg",
    "user": {
      "screen_name": "Forestwoodwood",
      "name": "FOREST ALBUM 🏳️‍🌈"
    },
    "media_type": "images",
    "url": "https://pbs.twimg.com/media/HIjRfMFaMAE4z9s.jpg",
    "read_time": "2026-05-18T06:01:57",
    "is_uploaded": true,
    "upload_info": {
      "success": true,
      "message_id": 24079,
      "timestamp": "2026-05-18T06:02:00"
    },
    "is_downloaded": true,
    "download_info": {
      "success": true,
      "size": 107859,
      "size_mb": 0.1,
      "timestamp": "2026-05-18T06:01:58",
      "download_attempts": 0
    },
    "full_text": "·\n微博的📷谢梓秋老师昨晚的新作品👍老师的笔记：“什么！？距离来工作室上次见，已经八年了！\n我严重怀疑这几年是不是地球 online 时间被拨快了🤦‍♂️ ​​​”\n\n男模是微博的@ Xiao熊快点跑 👍♥️ https://t.co/tU1mUufDTz",
    "publish_time": "2026-05-18T05:23:54"
  },
  {
    "file_name": "HIjRfMDboAAMUsh.jpg",
    "user": {
      "screen_name": "Forestwoodwood",
      "name": "FOREST ALBUM 🏳️‍🌈"
    },
    "media_type": "images",
    "url": "https://pbs.twimg.com/media/HIjRfMDboAAMUsh.jpg",
    "read_time": "2026-05-18T06:01:57",
    "is_uploaded": true,
    "upload_info": {
      "success": true,
      "message_id": 24080,
      "timestamp": "2026-05-18T06:02:01"
    },
    "is_downloaded": true,
    "download_info": {
      "success": true,
      "size": 103891,
      "size_mb": 0.1,
      "timestamp": "2026-05-18T06:02:00",
      "download_attempts": 0
    },
    "full_text": "·\n微博的📷谢梓秋老师昨晚的新作品👍老师的笔记：“什么！？距离来工作室上次见，已经八年了！\n我严重怀疑这几年是不是地球 online 时间被拨快了🤦‍♂️ ​​​”\n\n男模是微博的@ Xiao熊快点跑 👍♥️ https://t.co/tU1mUufDTz",
    "publish_time": "2026-05-18T05:23:54"
  },
  {
    "file_name": "HIjRfMFaMAA2zyG.jpg",
    "user": {
      "screen_name": "Forestwoodwood",
      "name": "FOREST ALBUM 🏳️‍🌈"
    },
    "media_type": "images",
    "url": "https://pbs.twimg.com/media/HIjRfMFaMAA2zyG.jpg",
    "read_time": "2026-05-18T06:01:57",
    "is_uploaded": true,
    "upload_info": {
      "success": true,
      "message_id": 24081,
      "timestamp": "2026-05-18T06:02:03"
    },
    "is_downloaded": true,
    "download_info": {
      "success": true,
      "size": 115611,
      "size_mb": 0.11,
      "timestamp": "2026-05-18T06:02:01",
      "download_attempts": 0
    },
    "full_text": "·\n微博的📷谢梓秋老师昨晚的新作品👍老师的笔记：“什么！？距离来工作室上次见，已经八年了！\n我严重怀疑这几年是不是地球 online 时间被拨快了🤦‍♂️ ​​​”\n\n男模是微博的@ Xiao熊快点跑 👍♥️ https://t.co/tU1mUufDTz",
    "publish_time": "2026-05-18T05:23:54"
  },
  {
    "file_name": "HIj8zGxbgAAxIXb.jpg",
    "user": {
      "screen_name": "Forestwoodwood",
      "name": "FOREST ALBUM 🏳️‍🌈"
    },
    "media_type": "images",
    "url": "https://pbs.twimg.com/media/HIj8zGxbgAAxIXb.jpg",
    "read_time": "2026-05-18T09:02:45",
    "is_uploaded": true,
    "upload_info": {
      "success": true,
      "message_id": 24082,
      "timestamp": "2026-05-18T09:02:48"
    },
    "is_downloaded": true,
    "download_info": {
      "success": true,
      "size": 185874,
      "size_mb": 0.18,
      "timestamp": "2026-05-18T09:02:46",
      "download_attempts": 0
    },
    "full_text": "·\n介绍一位健体哥｜北京小鹏 \n\nIG：xiao_peng84 👬🏻有对象了！\n摄影师IG：zhenfoto \n\n📍🇨🇳CHINA BEIJING https://t.co/sQpBUu8c4f",
    "publish_time": "2026-05-18T08:33:07"
  },
  {
    "file_name": "HIj8zGwbIAAwxAp.jpg",
    "user": {
      "screen_name": "Forestwoodwood",
      "name": "FOREST ALBUM 🏳️‍🌈"
    },
    "media_type": "images",
    "url": "https://pbs.twimg.com/media/HIj8zGwbIAAwxAp.jpg",
    "read_time": "2026-05-18T09:02:45",
    "is_uploaded": true,
    "upload_info": {
      "success": true,
      "message_id": 24083,
      "timestamp": "2026-05-18T09:02:50"
    },
    "is_downloaded": true,
    "download_info": {
      "success": true,
      "size": 229031,
      "size_mb": 0.22,
      "timestamp": "2026-05-18T09:02:48",
      "download_attempts": 0
    },
    "full_text": "·\n介绍一位健体哥｜北京小鹏 \n\nIG：xiao_peng84 👬🏻有对象了！\n摄影师IG：zhenfoto \n\n📍🇨🇳CHINA BEIJING https://t.co/sQpBUu8c4f",
    "publish_time": "2026-05-18T08:33:07"
  },
  {
    "file_name": "HIj8zGyaEAEnBQq.jpg",
    "user": {
      "screen_name": "Forestwoodwood",
      "name": "FOREST ALBUM 🏳️‍🌈"
    },
    "media_type": "images",
    "url": "https://pbs.twimg.com/media/HIj8zGyaEAEnBQq.jpg",
    "read_time": "2026-05-18T09:02:45",
    "is_uploaded": true,
    "upload_info": {
      "success": true,
      "message_id": 24084,
      "timestamp": "2026-05-18T09:02:52"
    },
    "is_downloaded": true,
    "download_info": {
      "success": true,
      "size": 206453,
      "size_mb": 0.2,
      "timestamp": "2026-05-18T09:02:51",
      "download_attempts": 0
    },
    "full_text": "·\n介绍一位健体哥｜北京小鹏 \n\nIG：xiao_peng84 👬🏻有对象了！\n摄影师IG：zhenfoto \n\n📍🇨🇳CHINA BEIJING https://t.co/sQpBUu8c4f",
    "publish_time": "2026-05-18T08:33:07"
  },
  {
    "file_name": "HIj84dib0AAbQLX.jpg",
    "user": {
      "screen_name": "Forestwoodwood",
      "name": "FOREST ALBUM 🏳️‍🌈"
    },
    "media_type": "images",
    "url": "https://pbs.twimg.com/media/HIj84dib0AAbQLX.jpg",
    "read_time": "2026-05-18T09:02:45",
    "is_uploaded": true,
    "upload_info": {
      "success": true,
      "message_id": 24085,
      "timestamp": "2026-05-18T09:02:54"
    },
    "is_downloaded": true,
    "download_info": {
      "success": true,
      "size": 145420,
      "size_mb": 0.14,
      "timestamp": "2026-05-18T09:02:52",
      "download_attempts": 0
    },
    "full_text": "https://t.co/vyEzKeOMDl",
    "publish_time": "2026-05-18T08:33:29"
  },
  {
    "file_name": "HIj84dhbsAAEe3_.jpg",
    "user": {
      "screen_name": "Forestwoodwood",
      "name": "FOREST ALBUM 🏳️‍🌈"
    },
    "media_type": "images",
    "url": "https://pbs.twimg.com/media/HIj84dhbsAAEe3_.jpg",
    "read_time": "2026-05-18T09:02:45",
    "is_uploaded": true,
    "upload_info": {
      "success": true,
      "message_id": 24086,
      "timestamp": "2026-05-18T09:02:55"
    },
    "is_downloaded": true,
    "download_info": {
      "success": true,
      "size": 117613,
      "size_mb": 0.11,
      "timestamp": "2026-05-18T09:02:54",
      "download_attempts": 0
    },
    "full_text": "https://t.co/vyEzKeOMDl",
    "publish_time": "2026-05-18T08:33:29"
  },
  {
    "file_name": "HIj84dha4AA72e9.jpg",
    "user": {
      "screen_name": "Forestwoodwood",
      "name": "FOREST ALBUM 🏳️‍🌈"
    },
    "media_type": "images",
    "url": "https://pbs.twimg.com/media/HIj84dha4AA72e9.jpg",
    "read_time": "2026-05-18T09:02:45",
    "is_uploaded": true,
    "upload_info": {
      "success": true,
      "message_id": 24087,
      "timestamp": "2026-05-18T09:02:56"
    },
    "is_downloaded": true,
    "download_info": {
      "success": true,
      "size": 168883,
      "size_mb": 0.16,
      "timestamp": "2026-05-18T09:02:55",
      "download_attempts": 0
    },
    "full_text": "https://t.co/vyEzKeOMDl",
    "publish_time": "2026-05-18T08:33:29"
  },
  {
    "file_name": "HIkIiN0bIAArCly.jpg",
    "user": {
      "screen_name": "Alstonyzh",
      "name": "奥格尼克"
    },
    "media_type": "images",
    "url": "https://pbs.twimg.com/media/HIkIiN0bIAArCly.jpg",
    "read_time": "2026-05-18T11:01:54",
    "is_uploaded": true,
    "upload_info": {
      "success": true,
      "message_id": 24088,
      "timestamp": "2026-05-18T11:01:57"
    },
    "is_downloaded": true,
    "download_info": {
      "success": true,
      "size": 221700,
      "size_mb": 0.21,
      "timestamp": "2026-05-18T11:01:55",
      "download_attempts": 0
    },
    "full_text": "😊 https://t.co/rN4EtdCtyR",
    "publish_time": "2026-05-18T09:24:50"
  },
  {
    "file_name": "HIkIlcqbwAA9wxs.jpg",
    "user": {
      "screen_name": "Alstonyzh",
      "name": "奥格尼克"
    },
    "media_type": "images",
    "url": "https://pbs.twimg.com/media/HIkIlcqbwAA9wxs.jpg",
    "read_time": "2026-05-18T11:01:54",
    "is_uploaded": true,
    "upload_info": {
      "success": true,
      "message_id": 24089,
      "timestamp": "2026-05-18T11:01:59"
    },
    "is_downloaded": true,
    "download_info": {
      "success": true,
      "size": 216221,
      "size_mb": 0.21,
      "timestamp": "2026-05-18T11:01:57",
      "download_attempts": 0
    },
    "full_text": "😊 https://t.co/rN4EtdCtyR",
    "publish_time": "2026-05-18T09:24:50"
  },
  {
    "file_name": "vx2qTuvJ6RKSu0J3.mp4",
    "user": {
      "screen_name": "BBoy1069",
      "name": "我是臭直男"
    },
    "media_type": "videos",
    "url": "https://video.twimg.com/amplify_video/2056198416804540416/vid/avc1/720x1356/vx2qTuvJ6RKSu0J3.mp4?tag=14",
    "read_time": "2026-05-18T11:01:54",
    "is_uploaded": true,
    "upload_info": {
      "success": true,
      "message_id": 24090,
      "timestamp": "2026-05-18T11:02:04"
    },
    "is_downloaded": true,
    "download_info": {
      "success": true,
      "size": 4438568,
      "size_mb": 4.23,
      "timestamp": "2026-05-18T11:02:01",
      "download_attempts": 0
    },
    "full_text": "【2026年5月18日】今日資源已經更新！以下視頻與更新資源無關！ https://t.co/KlZS3nfBPf",
    "publish_time": "2026-05-18T10:21:36"
  },
  {
    "file_name": "HIkYAMqbMAACtHq.jpg",
    "user": {
      "screen_name": "eric_kk97",
      "name": "ManFeed🍆"
    },
    "media_type": "images",
    "url": "https://pbs.twimg.com/media/HIkYAMqbMAACtHq.jpg",
    "read_time": "2026-05-18T11:01:54",
    "is_uploaded": true,
    "upload_info": {
      "success": true,
      "message_id": 24091,
      "timestamp": "2026-05-18T11:02:05"
    },
    "is_downloaded": true,
    "download_info": {
      "success": true,
      "size": 143283,
      "size_mb": 0.14,
      "timestamp": "2026-05-18T11:02:04",
      "download_attempts": 0
    },
    "full_text": "_eayon_ https://t.co/8EH9dOG4qe",
    "publish_time": "2026-05-18T10:31:59"
  },
  {
    "file_name": "HIkYWEibMAEn-AB.jpg",
    "user": {
      "screen_name": "eric_kk97",
      "name": "ManFeed🍆"
    },
    "media_type": "images",
    "url": "https://pbs.twimg.com/media/HIkYWEibMAEn-AB.jpg",
    "read_time": "2026-05-18T11:01:54",
    "is_uploaded": true,
    "upload_info": {
      "success": true,
      "message_id": 24092,
      "timestamp": "2026-05-18T11:02:06"
    },
    "is_downloaded": true,
    "download_info": {
      "success": true,
      "size": 167153,
      "size_mb": 0.16,
      "timestamp": "2026-05-18T11:02:05",
      "download_attempts": 0
    },
    "full_text": "https://t.co/Ltvh0JZQL7",
    "publish_time": "2026-05-18T10:33:29"
  },
  {
    "file_name": "HIkZfJOaYAAxQm-.jpg",
    "user": {
      "screen_name": "eric_kk97",
      "name": "ManFeed🍆"
    },
    "media_type": "images",
    "url": "https://pbs.twimg.com/media/HIkZfJOaYAAxQm-.jpg",
    "read_time": "2026-05-18T11:01:54",
    "is_uploaded": true,
    "upload_info": {
      "success": true,
      "message_id": 24093,
      "timestamp": "2026-05-18T11:02:07"
    },
    "is_downloaded": true,
    "download_info": {
      "success": true,
      "size": 203366,
      "size_mb": 0.19,
      "timestamp": "2026-05-18T11:02:06",
      "download_attempts": 0
    },
    "full_text": "https://t.co/uKPqNpS4v2",
    "publish_time": "2026-05-18T10:38:29"
  },
  {
    "file_name": "PUX2fParvenDhZu7.mp4",
    "user": {
      "screen_name": "max06734521",
      "name": "🪳大王🪳"
    },
    "media_type": "videos",
    "url": "https://video.twimg.com/amplify_video/2056238512937324544/vid/avc1/1280x502/PUX2fParvenDhZu7.mp4?tag=27",
    "read_time": "2026-05-18T13:01:51",
    "is_uploaded": true,
    "upload_info": {
      "success": true,
      "message_id": 24094,
      "timestamp": "2026-05-18T13:01:56"
    },
    "is_downloaded": true,
    "download_info": {
      "success": true,
      "size": 7494050,
      "size_mb": 7.15,
      "timestamp": "2026-05-18T13:01:52",
      "download_attempts": 0
    },
    "full_text": "再来一段喜欢的，🧊哥太难约了 https://t.co/ZCYJxiDebl",
    "publish_time": "2026-05-18T13:01:02"
  },
  {
    "file_name": "HIk6Q7OakAAGdMl.jpg",
    "user": {
      "screen_name": "LiugangLogan",
      "name": "刘刚Logan"
    },
    "media_type": "images",
    "url": "https://pbs.twimg.com/media/HIk6Q7OakAAGdMl.jpg",
    "read_time": "2026-05-18T14:02:18",
    "is_uploaded": true,
    "upload_info": {
      "success": true,
      "message_id": 24095,
      "timestamp": "2026-05-18T14:02:21"
    },
    "is_downloaded": true,
    "download_info": {
      "success": true,
      "size": 84522,
      "size_mb": 0.08,
      "timestamp": "2026-05-18T14:02:19",
      "download_attempts": 0
    },
    "full_text": "https://t.co/BltS20XseU",
    "publish_time": "2026-05-18T13:01:43"
  },
  {
    "file_name": "HIk8T9IboAArr0R.jpg",
    "user": {
      "screen_name": "liangguai1",
      "name": "亮拐"
    },
    "media_type": "images",
    "url": "https://pbs.twimg.com/media/HIk8T9IboAArr0R.jpg",
    "read_time": "2026-05-18T14:02:18",
    "is_uploaded": true,
    "upload_info": {
      "success": true,
      "message_id": 24096,
      "timestamp": "2026-05-18T14:02:22"
    },
    "is_downloaded": true,
    "download_info": {
      "success": true,
      "size": 176905,
      "size_mb": 0.17,
      "timestamp": "2026-05-18T14:02:21",
      "download_attempts": 0
    },
    "full_text": "https://t.co/yJU9zYLNh4",
    "publish_time": "2026-05-18T13:10:39"
  },
  {
    "file_name": "FzZ5t0uUnIiGQSud.mp4",
    "user": {
      "screen_name": "Azrael64300",
      "name": "薅壕好昊"
    },
    "media_type": "videos",
    "url": "https://video.twimg.com/amplify_video/2056203058804330496/vid/avc1/720x1280/FzZ5t0uUnIiGQSud.mp4?tag=14",
    "read_time": "2026-05-18T14:02:18",
    "is_uploaded": true,
    "upload_info": {
      "success": true,
      "message_id": 24097,
      "timestamp": "2026-05-18T14:02:25"
    },
    "is_downloaded": true,
    "download_info": {
      "success": true,
      "size": 6487721,
      "size_mb": 6.19,
      "timestamp": "2026-05-18T14:02:22",
      "download_attempts": 0
    },
    "full_text": "https://t.co/O5Vka90EqH",
    "publish_time": "2026-05-18T13:28:20"
  },
  {
    "file_name": "HIlGwTqb0AAj7l3.mp4",
    "user": {
      "screen_name": "neon385908",
      "name": "ne on"
    },
    "media_type": "videos",
    "url": "https://video.twimg.com/tweet_video/HIlGwTqb0AAj7l3.mp4",
    "read_time": "2026-05-18T14:02:18",
    "is_uploaded": true,
    "upload_info": {
      "success": true,
      "message_id": 24098,
      "timestamp": "2026-05-18T14:02:26"
    },
    "is_downloaded": true,
    "download_info": {
      "success": true,
      "size": 79663,
      "size_mb": 0.08,
      "timestamp": "2026-05-18T14:02:25",
      "download_attempts": 0
    },
    "full_text": "萌 https://t.co/TFFUY1uQt6",
    "publish_time": "2026-05-18T13:56:36"
  },
  {
    "file_name": "HIlLwAGaAAAOR0o.jpg",
    "user": {
      "screen_name": "MuscleFlexGod",
      "name": "Muscle Fighter"
    },
    "media_type": "images",
    "url": "https://pbs.twimg.com/media/HIlLwAGaAAAOR0o.jpg",
    "read_time": "2026-05-18T15:01:48",
    "is_uploaded": true,
    "upload_info": {
      "success": true,
      "message_id": 24099,
      "timestamp": "2026-05-18T15:01:50"
    },
    "is_downloaded": true,
    "download_info": {
      "success": true,
      "size": 107046,
      "size_mb": 0.1,
      "timestamp": "2026-05-18T15:01:48",
      "download_attempts": 0
    },
    "full_text": "https://t.co/xZnDdrXmFw",
    "publish_time": "2026-05-18T14:18:04"
  },
  {
    "file_name": "HIlXT3vWMAANXNV.jpg",
    "user": {
      "screen_name": "chounizadi2021",
      "name": "男神传送门"
    },
    "media_type": "images",
    "url": "https://pbs.twimg.com/media/HIlXT3vWMAANXNV.jpg",
    "read_time": "2026-05-18T16:02:42",
    "is_uploaded": true,
    "upload_info": {
      "success": true,
      "message_id": 24100,
      "timestamp": "2026-05-18T16:02:45"
    },
    "is_downloaded": true,
    "download_info": {
      "success": true,
      "size": 154941,
      "size_mb": 0.15,
      "timestamp": "2026-05-18T16:02:43",
      "download_attempts": 0
    },
    "full_text": "【粉丝投稿】谁知道这个是谁，知道社交账号的请私信。第一个私信开门的可以免费寻人。（发帖寻人收费🧧，vpn不稳定，寻人/征友/买男性用品加个人VX（SYLjiankang2023），注明来意否则不通过） https://t.co/1jtUEliyNg",
    "publish_time": "2026-05-18T15:08:38"
  },
  {
    "file_name": "HIlYroUboAAA2q0.jpg",
    "user": {
      "screen_name": "SZionbaba",
      "name": "zionbaba"
    },
    "media_type": "images",
    "url": "https://pbs.twimg.com/media/HIlYroUboAAA2q0.jpg",
    "read_time": "2026-05-18T16:02:42",
    "is_uploaded": true,
    "upload_info": {
      "success": true,
      "message_id": 24101,
      "timestamp": "2026-05-18T16:02:47"
    },
    "is_downloaded": true,
    "download_info": {
      "success": true,
      "size": 177610,
      "size_mb": 0.17,
      "timestamp": "2026-05-18T16:02:45",
      "download_attempts": 0
    },
    "full_text": "从哪里开始舔？ https://t.co/I70isyedCr",
    "publish_time": "2026-05-18T15:14:37"
  },
  {
    "file_name": "HIlYr3ia4AAFQar.jpg",
    "user": {
      "screen_name": "SZionbaba",
      "name": "zionbaba"
    },
    "media_type": "images",
    "url": "https://pbs.twimg.com/media/HIlYr3ia4AAFQar.jpg",
    "read_time": "2026-05-18T16:02:42",
    "is_uploaded": true,
    "upload_info": {
      "success": true,
      "message_id": 24102,
      "timestamp": "2026-05-18T16:02:48"
    },
    "is_downloaded": true,
    "download_info": {
      "success": true,
      "size": 130014,
      "size_mb": 0.12,
      "timestamp": "2026-05-18T16:02:47",
      "download_attempts": 0
    },
    "full_text": "从哪里开始舔？ https://t.co/I70isyedCr",
    "publish_time": "2026-05-18T15:14:37"
  },
  {
    "file_name": "HIlYrnKaYAAEaHB.jpg",
    "user": {
      "screen_name": "SZionbaba",
      "name": "zionbaba"
    },
    "media_type": "images",
    "url": "https://pbs.twimg.com/media/HIlYrnKaYAAEaHB.jpg",
    "read_time": "2026-05-18T16:02:42",
    "is_uploaded": true,
    "upload_info": {
      "success": true,
      "message_id": 24103,
      "timestamp": "2026-05-18T16:02:50"
    },
    "is_downloaded": true,
    "download_info": {
      "success": true,
      "size": 107020,
      "size_mb": 0.1,
      "timestamp": "2026-05-18T16:02:48",
      "download_attempts": 0
    },
    "full_text": "从哪里开始舔？ https://t.co/I70isyedCr",
    "publish_time": "2026-05-18T15:14:37"
  },
  {
    "file_name": "vC6NFAnrg0SsIYfC.mp4",
    "user": {
      "screen_name": "bohaixiaochen",
      "name": "芋泥再多加芋圆"
    },
    "media_type": "videos",
    "url": "https://video.twimg.com/ext_tw_video/2056279920607891456/pu/vid/avc1/720x1280/vC6NFAnrg0SsIYfC.mp4?tag=12",
    "read_time": "2026-05-18T16:02:42",
    "is_uploaded": true,
    "upload_info": {
      "success": true,
      "message_id": 24104,
      "timestamp": "2026-05-18T16:02:52"
    },
    "is_downloaded": true,
    "download_info": {
      "success": true,
      "size": 420882,
      "size_mb": 0.4,
      "timestamp": "2026-05-18T16:02:51",
      "download_attempts": 0
    },
    "full_text": "午后顶顶🔝🔝🔝 https://t.co/MYkN84i6Kz",
    "publish_time": "2026-05-18T15:45:24"
  },
  {
    "file_name": "pi6YrZO4fyJUoToJ.mp4",
    "user": {
      "screen_name": "bohaixiaochen",
      "name": "芋泥再多加芋圆"
    },
    "media_type": "videos",
    "url": "https://video.twimg.com/ext_tw_video/2056279924416417792/pu/vid/avc1/720x1280/pi6YrZO4fyJUoToJ.mp4?tag=12",
    "read_time": "2026-05-18T16:02:42",
    "is_uploaded": true,
    "upload_info": {
      "success": true,
      "message_id": 24105,
      "timestamp": "2026-05-18T16:02:54"
    },
    "is_downloaded": true,
    "download_info": {
      "success": true,
      "size": 251023,
      "size_mb": 0.24,
      "timestamp": "2026-05-18T16:02:52",
      "download_attempts": 0
    },
    "full_text": "午后顶顶🔝🔝🔝 https://t.co/MYkN84i6Kz",
    "publish_time": "2026-05-18T15:45:24"
  },
  {
    "file_name": "Jv4i_nRv3z2N83FA.mp4",
    "user": {
      "screen_name": "bohaixiaochen",
      "name": "芋泥再多加芋圆"
    },
    "media_type": "videos",
    "url": "https://video.twimg.com/ext_tw_video/2056279928065470464/pu/vid/avc1/1280x720/Jv4i_nRv3z2N83FA.mp4?tag=12",
    "read_time": "2026-05-18T16:02:42",
    "is_uploaded": true,
    "upload_info": {
      "success": true,
      "message_id": 24106,
      "timestamp": "2026-05-18T16:02:56"
    },
    "is_downloaded": true,
    "download_info": {
      "success": true,
      "size": 396266,
      "size_mb": 0.38,
      "timestamp": "2026-05-18T16:02:55",
      "download_attempts": 0
    },
    "full_text": "午后顶顶🔝🔝🔝 https://t.co/MYkN84i6Kz",
    "publish_time": "2026-05-18T15:45:24"
  },
  {
    "file_name": "aLFKwHkAdUbauZQY.mp4",
    "user": {
      "screen_name": "bohaixiaochen",
      "name": "芋泥再多加芋圆"
    },
    "media_type": "videos",
    "url": "https://video.twimg.com/ext_tw_video/2056279958000201728/pu/vid/avc1/1280x720/aLFKwHkAdUbauZQY.mp4?tag=12",
    "read_time": "2026-05-18T16:02:42",
    "is_uploaded": true,
    "upload_info": {
      "success": true,
      "message_id": 24107,
      "timestamp": "2026-05-18T16:02:57"
    },
    "is_downloaded": true,
    "download_info": {
      "success": true,
      "size": 337174,
      "size_mb": 0.32,
      "timestamp": "2026-05-18T16:02:56",
      "download_attempts": 0
    },
    "full_text": "午后顶顶🔝🔝🔝 https://t.co/MYkN84i6Kz",
    "publish_time": "2026-05-18T15:45:24"
  },
  {
    "file_name": "HIlf28fawAAI3wV.jpg",
    "user": {
      "screen_name": "zuoximuhao1111S",
      "name": "佐夕木豪"
    },
    "media_type": "images",
    "url": "https://pbs.twimg.com/media/HIlf28fawAAI3wV.jpg",
    "read_time": "2026-05-18T16:02:42",
    "is_uploaded": true,
    "upload_info": {
      "success": true,
      "message_id": 24108,
      "timestamp": "2026-05-18T16:02:58"
    },
    "is_downloaded": true,
    "download_info": {
      "success": true,
      "size": 195393,
      "size_mb": 0.19,
      "timestamp": "2026-05-18T16:02:57",
      "download_attempts": 0
    },
    "full_text": "一张蓝色相片🌊 https://t.co/J0C6xcwedn",
    "publish_time": "2026-05-18T15:45:57"
  },
  {
    "file_name": "HIlf7LUaAAAERW3.jpg",
    "user": {
      "screen_name": "eric_kk97",
      "name": "ManFeed🍆"
    },
    "media_type": "images",
    "url": "https://pbs.twimg.com/media/HIlf7LUaAAAERW3.jpg",
    "read_time": "2026-05-18T16:02:42",
    "is_uploaded": true,
    "upload_info": {
      "success": true,
      "message_id": 24109,
      "timestamp": "2026-05-18T16:02:59"
    },
    "is_downloaded": true,
    "download_info": {
      "success": true,
      "size": 137062,
      "size_mb": 0.13,
      "timestamp": "2026-05-18T16:02:58",
      "download_attempts": 0
    },
    "full_text": "https://t.co/l8UyHxvCAD",
    "publish_time": "2026-05-18T15:46:13"
  },
  {
    "file_name": "WOGGMVAfsm8fGBC_.mp4",
    "user": {
      "screen_name": "fanglangnantu",
      "name": "NANTU"
    },
    "media_type": "videos",
    "url": "https://video.twimg.com/amplify_video/2056282467347357696/vid/avc1/720x960/WOGGMVAfsm8fGBC_.mp4?tag=27",
    "read_time": "2026-05-18T16:02:42",
    "is_uploaded": true,
    "upload_info": {
      "success": true,
      "message_id": 24110,
      "timestamp": "2026-05-18T16:03:01"
    },
    "is_downloaded": true,
    "download_info": {
      "success": true,
      "size": 421772,
      "size_mb": 0.4,
      "timestamp": "2026-05-18T16:03:00",
      "download_attempts": 0
    },
    "full_text": "I Love Beijing 🔥 My Lucky City https://t.co/oGf8Y9kjl4",
    "publish_time": "2026-05-18T15:55:25"
  },
  {
    "file_name": "HIlk2h7aUAAQrYm.jpg",
    "user": {
      "screen_name": "eric_kk97",
      "name": "ManFeed🍆"
    },
    "media_type": "images",
    "url": "https://pbs.twimg.com/media/HIlk2h7aUAAQrYm.jpg",
    "read_time": "2026-05-18T17:02:06",
    "is_uploaded": true,
    "upload_info": {
      "success": true,
      "message_id": 24111,
      "timestamp": "2026-05-18T17:02:09"
    },
    "is_downloaded": true,
    "download_info": {
      "success": true,
      "size": 266593,
      "size_mb": 0.25,
      "timestamp": "2026-05-18T17:02:07",
      "download_attempts": 0
    },
    "full_text": "https://t.co/4T0I6OYIrD",
    "publish_time": "2026-05-18T16:07:45"
  },
  {
    "file_name": "HIlwA7JbAAAiZ2l.jpg",
    "user": {
      "screen_name": "JAX23632335",
      "name": "xx"
    },
    "media_type": "images",
    "url": "https://pbs.twimg.com/media/HIlwA7JbAAAiZ2l.jpg",
    "read_time": "2026-05-18T17:02:06",
    "is_uploaded": true,
    "upload_info": {
      "success": true,
      "message_id": 24112,
      "timestamp": "2026-05-18T17:02:11"
    },
    "is_downloaded": true,
    "download_info": {
      "success": true,
      "size": 109125,
      "size_mb": 0.1,
      "timestamp": "2026-05-18T17:02:10",
      "download_attempts": 0
    },
    "full_text": "今天好累喔\n大雞雞都給我出來道歉喔 https://t.co/sHUJ2zSnUR",
    "publish_time": "2026-05-18T16:56:32"
  },
  {
    "file_name": "HIlwPXDaMAAYM-1.jpg",
    "user": {
      "screen_name": "MaryBak64398222",
      "name": "直男调教s"
    },
    "media_type": "images",
    "url": "https://pbs.twimg.com/media/HIlwPXDaMAAYM-1.jpg",
    "read_time": "2026-05-18T17:02:06",
    "is_uploaded": true,
    "upload_info": {
      "success": true,
      "message_id": 24113,
      "timestamp": "2026-05-18T17:02:11"
    },
    "is_downloaded": true,
    "download_info": {
      "success": true,
      "size": 7512,
      "size_mb": 0.01,
      "timestamp": "2026-05-18T17:02:11",
      "download_attempts": 0
    },
    "full_text": "本来开开心心的上号准备更新~ \n结果再次喜迎举报大礼包😃 吃水还不忘挖井人呢，实属是一群没良心的剑币\n\n告密的、嫉妒的同好随便来~ 让你们免费观赏还恶心我，号就算没了也无所谓，正好搞一个私密号更新，想看就掏钱付费😄净给你们一些白嫖剑币惯的毛病，看那些烂大街的网站资源去吧，莎比东西 https://t.co/K7qbNQDRwE",
    "publish_time": "2026-05-18T16:57:29"
  },
  {
    "file_name": "HIlzTTfbkAAfmVy.jpg",
    "user": {
      "screen_name": "zhozho622075",
      "name": "biofrost"
    },
    "media_type": "images",
    "url": "https://pbs.twimg.com/media/HIlzTTfbkAAfmVy.jpg",
    "read_time": "2026-05-18T18:02:08",
    "is_uploaded": true,
    "upload_info": {
      "success": true,
      "message_id": 24114,
      "timestamp": "2026-05-18T18:02:11"
    },
    "is_downloaded": true,
    "download_info": {
      "success": true,
      "size": 66135,
      "size_mb": 0.06,
      "timestamp": "2026-05-18T18:02:09",
      "download_attempts": 0
    },
    "full_text": "最近迷上了拍寫真！以前的黃推都隱藏了，短期不會放出來 https://t.co/AfhU5qXyQr",
    "publish_time": "2026-05-18T17:10:54"
  },
  {
    "file_name": "HIlzTTZaQAAdCCx.jpg",
    "user": {
      "screen_name": "zhozho622075",
      "name": "biofrost"
    },
    "media_type": "images",
    "url": "https://pbs.twimg.com/media/HIlzTTZaQAAdCCx.jpg",
    "read_time": "2026-05-18T18:02:08",
    "is_uploaded": true,
    "upload_info": {
      "success": true,
      "message_id": 24115,
      "timestamp": "2026-05-18T18:02:13"
    },
    "is_downloaded": true,
    "download_info": {
      "success": true,
      "size": 76915,
      "size_mb": 0.07,
      "timestamp": "2026-05-18T18:02:11",
      "download_attempts": 0
    },
    "full_text": "最近迷上了拍寫真！以前的黃推都隱藏了，短期不會放出來 https://t.co/AfhU5qXyQr",
    "publish_time": "2026-05-18T17:10:54"
  },
  {
    "file_name": "HIl0LaMbIAAIDcJ.jpg",
    "user": {
      "screen_name": "Wanfeng549513",
      "name": "如何挽风"
    },
    "media_type": "images",
    "url": "https://pbs.twimg.com/media/HIl0LaMbIAAIDcJ.jpg",
    "read_time": "2026-05-18T18:02:08",
    "is_uploaded": true,
    "upload_info": {
      "success": true,
      "message_id": 24116,
      "timestamp": "2026-05-18T18:02:15"
    },
    "is_downloaded": true,
    "download_info": {
      "success": true,
      "size": 86930,
      "size_mb": 0.08,
      "timestamp": "2026-05-18T18:02:13",
      "download_attempts": 0
    },
    "full_text": "喜欢看着北口 #醇野挽风 \n\nI like watching you lick me. https://t.co/Y0mkczdGar",
    "publish_time": "2026-05-18T17:14:44"
  },
  {
    "file_name": "HIl9TV5aoAAXuhW.jpg",
    "user": {
      "screen_name": "Wanfeng549513",
      "name": "如何挽风"
    },
    "media_type": "images",
    "url": "https://pbs.twimg.com/media/HIl9TV5aoAAXuhW.jpg",
    "read_time": "2026-05-18T18:02:08",
    "is_uploaded": true,
    "upload_info": {
      "success": true,
      "message_id": 24117,
      "timestamp": "2026-05-18T18:02:16"
    },
    "is_downloaded": true,
    "download_info": {
      "success": true,
      "size": 62990,
      "size_mb": 0.06,
      "timestamp": "2026-05-18T18:02:15",
      "download_attempts": 0
    },
    "full_text": "不喜欢太多口水，喜欢有一些摩擦感\n#醇野挽风 \n\nI don't like drooling too much, I like some friction. https://t.co/LeVfSpW62h",
    "publish_time": "2026-05-18T17:54:35"
  },
  {
    "file_name": "HIl97u9bEAAjCkN.jpg",
    "user": {
      "screen_name": "eric_kk97",
      "name": "ManFeed🍆"
    },
    "media_type": "images",
    "url": "https://pbs.twimg.com/media/HIl97u9bEAAjCkN.jpg",
    "read_time": "2026-05-18T18:02:08",
    "is_uploaded": true,
    "upload_info": {
      "success": true,
      "message_id": 24118,
      "timestamp": "2026-05-18T18:02:18"
    },
    "is_downloaded": true,
    "download_info": {
      "success": true,
      "size": 130182,
      "size_mb": 0.12,
      "timestamp": "2026-05-18T18:02:16",
      "download_attempts": 0
    },
    "full_text": "https://t.co/BXd6XQiAVp",
    "publish_time": "2026-05-18T17:57:20"
  },
  {
    "file_name": "vmNFd68JAGZJyeb2.mp4",
    "user": {
      "screen_name": "SPHYNX688",
      "name": "无脸猫SPHYNX"
    },
    "media_type": "videos",
    "url": "https://video.twimg.com/amplify_video/2054203921099522048/vid/avc1/720x720/vmNFd68JAGZJyeb2.mp4?tag=14",
    "read_time": "2026-05-18T19:02:06",
    "is_uploaded": true,
    "upload_info": {
      "success": true,
      "message_id": 24119,
      "timestamp": "2026-05-18T19:02:11"
    },
    "is_downloaded": true,
    "download_info": {
      "success": true,
      "size": 10643928,
      "size_mb": 10.15,
      "timestamp": "2026-05-18T19:02:08",
      "download_attempts": 0
    },
    "full_text": "有没有类似的1s博主 https://t.co/lYQxDSKfoY",
    "publish_time": "2026-05-18T18:28:18"
  },
  {
    "file_name": "HImO_VpbEAAuKVb.jpg",
    "user": {
      "screen_name": "Xiongdaha",
      "name": "帕丁顿熊（成都）"
    },
    "media_type": "images",
    "url": "https://pbs.twimg.com/media/HImO_VpbEAAuKVb.jpg",
    "read_time": "2026-05-18T21:02:04",
    "is_uploaded": true,
    "upload_info": {
      "success": true,
      "message_id": 24120,
      "timestamp": "2026-05-18T21:02:06"
    },
    "is_downloaded": true,
    "download_info": {
      "success": true,
      "size": 44595,
      "size_mb": 0.04,
      "timestamp": "2026-05-18T21:02:04",
      "download_attempts": 0
    },
    "full_text": "两张red. https://t.co/FQQCG3OrQP",
    "publish_time": "2026-05-18T19:12:06"
  },
  {
    "file_name": "HImO_VVboAEQa03.jpg",
    "user": {
      "screen_name": "Xiongdaha",
      "name": "帕丁顿熊（成都）"
    },
    "media_type": "images",
    "url": "https://pbs.twimg.com/media/HImO_VVboAEQa03.jpg",
    "read_time": "2026-05-18T21:02:04",
    "is_uploaded": true,
    "upload_info": {
      "success": true,
      "message_id": 24121,
      "timestamp": "2026-05-18T21:02:08"
    },
    "is_downloaded": true,
    "download_info": {
      "success": true,
      "size": 47963,
      "size_mb": 0.05,
      "timestamp": "2026-05-18T21:02:06",
      "download_attempts": 0
    },
    "full_text": "两张red. https://t.co/FQQCG3OrQP",
    "publish_time": "2026-05-18T19:12:06"
  },
  {
    "file_name": "HImTiBFa0AAPKsO.jpg",
    "user": {
      "screen_name": "youdi",
      "name": "HARUEHUN AIRRY 王子部落"
    },
    "media_type": "images",
    "url": "https://pbs.twimg.com/media/HImTiBFa0AAPKsO.jpg",
    "read_time": "2026-05-18T21:02:04",
    "is_uploaded": true,
    "upload_info": {
      "success": true,
      "message_id": 24122,
      "timestamp": "2026-05-18T21:02:10"
    },
    "is_downloaded": true,
    "download_info": {
      "success": true,
      "size": 118182,
      "size_mb": 0.11,
      "timestamp": "2026-05-18T21:02:08",
      "download_attempts": 0
    },
    "full_text": "https://t.co/3vBBsCDi3l",
    "publish_time": "2026-05-18T19:31:44"
  },
  {
    "file_name": "HIma6rhbAAEFnOc.jpg",
    "user": {
      "screen_name": "YCJ2023",
      "name": "杨长进"
    },
    "media_type": "images",
    "url": "https://pbs.twimg.com/media/HIma6rhbAAEFnOc.jpg",
    "read_time": "2026-05-18T21:02:04",
    "is_uploaded": true,
    "upload_info": {
      "success": true,
      "message_id": 24123,
      "timestamp": "2026-05-18T21:02:11"
    },
    "is_downloaded": true,
    "download_info": {
      "success": true,
      "size": 208201,
      "size_mb": 0.2,
      "timestamp": "2026-05-18T21:02:10",
      "download_attempts": 0
    },
    "full_text": "丝袜🙋‍♂️ https://t.co/r9xuuSFtON",
    "publish_time": "2026-05-18T20:03:58"
  },
  {
    "file_name": "TxvHVLM1OfpaGwuO.mp4",
    "user": {
      "screen_name": "xxjy9696",
      "name": "小小脚丫🐾全见版（新）"
    },
    "media_type": "videos",
    "url": "https://video.twimg.com/amplify_video/2056347382447808512/vid/avc1/720x1280/TxvHVLM1OfpaGwuO.mp4?tag=27",
    "read_time": "2026-05-18T21:02:04",
    "is_uploaded": true,
    "upload_info": {
      "success": true,
      "message_id": 24124,
      "timestamp": "2026-05-18T21:02:17"
    },
    "is_downloaded": true,
    "download_info": {
      "success": true,
      "size": 8213677,
      "size_mb": 7.83,
      "timestamp": "2026-05-18T21:02:13",
      "download_attempts": 0
    },
    "full_text": "🫟蒙古野驹❸🫟\n🫥千呼万唤始出来！蒙古壮屌熊爹出来和姐姐偷情啦！上次被他老婆发现，被删了，结果一出差在民宿，鸡巴立刻硬的要找姐姐释放…快半年没射了！这次精量大到吓人，他和他老婆没感情，只能默默地等喜欢姐姐的逼，他只要一看，鸡巴硬的像个棒槌~那姐就狠狠满足了他，正好你们催\n#蒙古野驹3 https://t.co/ulxRlVIuC0",
    "publish_time": "2026-05-18T20:15:10"
  },
  {
    "file_name": "17rp9iCFaiQWafQt.mp4",
    "user": {
      "screen_name": "paeching",
      "name": "屁吃"
    },
    "media_type": "videos",
    "url": "https://video.twimg.com/amplify_video/2056360761388306433/vid/avc1/688x960/17rp9iCFaiQWafQt.mp4?tag=27",
    "read_time": "2026-05-18T22:02:18",
    "is_uploaded": true,
    "upload_info": {
      "success": true,
      "message_id": 24125,
      "timestamp": "2026-05-18T22:02:22"
    },
    "is_downloaded": true,
    "download_info": {
      "success": true,
      "size": 841717,
      "size_mb": 0.8,
      "timestamp": "2026-05-18T22:02:19",
      "download_attempts": 0
    },
    "full_text": "👅🦶🏻 https://t.co/gaNw4PUb8d",
    "publish_time": "2026-05-18T21:06:36"
  },
  {
    "file_name": "HImrOMaXoAAbcg6.jpg",
    "user": {
      "screen_name": "chounizadi2021",
      "name": "男神传送门"
    },
    "media_type": "images",
    "url": "https://pbs.twimg.com/media/HImrOMaXoAAbcg6.jpg",
    "read_time": "2026-05-18T22:02:18",
    "is_uploaded": true,
    "upload_info": {
      "success": true,
      "message_id": 24126,
      "timestamp": "2026-05-18T22:02:23"
    },
    "is_downloaded": true,
    "download_info": {
      "success": true,
      "size": 291734,
      "size_mb": 0.28,
      "timestamp": "2026-05-18T22:02:22",
      "download_attempts": 0
    },
    "full_text": "继续安利《给阿嬷的情书》，不是爱情，不苦情，是讲情义，近些年最好看的电影，没有之一。 https://t.co/biE4O6pTwK",
    "publish_time": "2026-05-18T21:15:15"
  },
  {
    "file_name": "HImrOMcW4AA3fBp.jpg",
    "user": {
      "screen_name": "chounizadi2021",
      "name": "男神传送门"
    },
    "media_type": "images",
    "url": "https://pbs.twimg.com/media/HImrOMcW4AA3fBp.jpg",
    "read_time": "2026-05-18T22:02:18",
    "is_uploaded": true,
    "upload_info": {
      "success": true,
      "message_id": 24127,
      "timestamp": "2026-05-18T22:02:24"
    },
    "is_downloaded": true,
    "download_info": {
      "success": true,
      "size": 110034,
      "size_mb": 0.1,
      "timestamp": "2026-05-18T22:02:23",
      "download_attempts": 0
    },
    "full_text": "继续安利《给阿嬷的情书》，不是爱情，不苦情，是讲情义，近些年最好看的电影，没有之一。 https://t.co/biE4O6pTwK",
    "publish_time": "2026-05-18T21:15:15"
  },
  {
    "file_name": "HImyDMqakAAsLK8.jpg",
    "user": {
      "screen_name": "Doraemonphoto",
      "name": "Doraemon"
    },
    "media_type": "images",
    "url": "https://pbs.twimg.com/media/HImyDMqakAAsLK8.jpg",
    "read_time": "2026-05-18T22:02:18",
    "is_uploaded": true,
    "upload_info": {
      "success": true,
      "message_id": 24128,
      "timestamp": "2026-05-18T22:02:25"
    },
    "is_downloaded": true,
    "download_info": {
      "success": true,
      "size": 126325,
      "size_mb": 0.12,
      "timestamp": "2026-05-18T22:02:24",
      "download_attempts": 0
    },
    "full_text": "全👀 https://t.co/pv3iHuExSf",
    "publish_time": "2026-05-18T21:45:17"
  },
  {
    "file_name": "-b81IgahCaLmcx2L.mp4",
    "user": {
      "screen_name": "sx84604818",
      "name": "Rexsonic Man+ suits & socks"
    },
    "media_type": "videos",
    "url": "https://video.twimg.com/amplify_video/2056372776022470656/vid/avc1/1280x720/-b81IgahCaLmcx2L.mp4?tag=27",
    "read_time": "2026-05-18T22:02:18",
    "is_uploaded": true,
    "upload_info": {
      "success": true,
      "message_id": 24129,
      "timestamp": "2026-05-18T22:02:28"
    },
    "is_downloaded": true,
    "download_info": {
      "success": true,
      "size": 4368096,
      "size_mb": 4.17,
      "timestamp": "2026-05-18T22:02:26",
      "download_attempts": 0
    },
    "full_text": "👔西裝愛好者👔 https://t.co/xLkk31bSPp",
    "publish_time": "2026-05-18T21:54:19"
  }
]