[
  {
    "file_name": "HINhg6qboAAmsGj.jpg",
    "user": {
      "screen_name": "bohaixiaochen",
      "name": "иҠӢжіҘеҶҚеӨҡеҠ иҠӢеңҶ"
    },
    "media_type": "images",
    "url": "https://pbs.twimg.com/media/HINhg6qboAAmsGj.jpg",
    "read_time": "2026-05-14T01:02:59",
    "is_uploaded": true,
    "upload_info": {
      "success": true,
      "message_id": 23709,
      "timestamp": "2026-05-14T01:03:14"
    },
    "is_downloaded": true,
    "download_info": {
      "success": true,
      "size": 94849,
      "size_mb": 0.09,
      "timestamp": "2026-05-14T01:03:13",
      "download_attempts": 0
    },
    "full_text": "й…’зІҫдёҠеӨҙзҺ©дәҶеҘҪд№… еҫҲin https://t.co/LVM8hsngi4",
    "publish_time": "2026-05-14T00:02:16"
  },
  {
    "file_name": "HINhg6HacAEeX-O.jpg",
    "user": {
      "screen_name": "bohaixiaochen",
      "name": "иҠӢжіҘеҶҚеӨҡеҠ иҠӢеңҶ"
    },
    "media_type": "images",
    "url": "https://pbs.twimg.com/media/HINhg6HacAEeX-O.jpg",
    "read_time": "2026-05-14T01:02:59",
    "is_uploaded": true,
    "upload_info": {
      "success": true,
      "message_id": 23710,
      "timestamp": "2026-05-14T01:03:15"
    },
    "is_downloaded": true,
    "download_info": {
      "success": true,
      "size": 105627,
      "size_mb": 0.1,
      "timestamp": "2026-05-14T01:03:14",
      "download_attempts": 0
    },
    "full_text": "й…’зІҫдёҠеӨҙзҺ©дәҶеҘҪд№… еҫҲin https://t.co/LVM8hsngi4",
    "publish_time": "2026-05-14T00:02:16"
  },
  {
    "file_name": "HINhg_gbcAAQrLr.jpg",
    "user": {
      "screen_name": "bohaixiaochen",
      "name": "иҠӢжіҘеҶҚеӨҡеҠ иҠӢеңҶ"
    },
    "media_type": "images",
    "url": "https://pbs.twimg.com/media/HINhg_gbcAAQrLr.jpg",
    "read_time": "2026-05-14T01:02:59",
    "is_uploaded": true,
    "upload_info": {
      "success": true,
      "message_id": 23711,
      "timestamp": "2026-05-14T01:03:16"
    },
    "is_downloaded": true,
    "download_info": {
      "success": true,
      "size": 124178,
      "size_mb": 0.12,
      "timestamp": "2026-05-14T01:03:15",
      "download_attempts": 0
    },
    "full_text": "й…’зІҫдёҠеӨҙзҺ©дәҶеҘҪд№… еҫҲin https://t.co/LVM8hsngi4",
    "publish_time": "2026-05-14T00:02:16"
  },
  {
    "file_name": "z9TJyFmSrOtNUUMl.mp4",
    "user": {
      "screen_name": "kaka_lac",
      "name": "kaka"
    },
    "media_type": "videos",
    "url": "https://video.twimg.com/amplify_video/2054603006650589185/vid/avc1/544x960/z9TJyFmSrOtNUUMl.mp4?tag=27",
    "read_time": "2026-05-14T01:02:59",
    "is_uploaded": true,
    "upload_info": {
      "success": true,
      "message_id": 23712,
      "timestamp": "2026-05-14T01:03:18"
    },
    "is_downloaded": true,
    "download_info": {
      "success": true,
      "size": 908229,
      "size_mb": 0.87,
      "timestamp": "2026-05-14T01:03:16",
      "download_attempts": 0
    },
    "full_text": "https://t.co/z0fep8FuSe",
    "publish_time": "2026-05-14T00:41:58"
  },
  {
    "file_name": "X7NQo5l7JHHjaYe8.mp4",
    "user": {
      "screen_name": "wangsan82l",
      "name": "зҺӢеҲ©еҚҺзҡ„йј ж Ү"
    },
    "media_type": "videos",
    "url": "https://video.twimg.com/amplify_video/2054606465441177600/vid/avc1/720x1280/X7NQo5l7JHHjaYe8.mp4?tag=27",
    "read_time": "2026-05-14T01:02:59",
    "is_uploaded": true,
    "upload_info": {
      "success": true,
      "message_id": 23713,
      "timestamp": "2026-05-14T01:03:20"
    },
    "is_downloaded": true,
    "download_info": {
      "success": true,
      "size": 1278230,
      "size_mb": 1.22,
      "timestamp": "2026-05-14T01:03:19",
      "download_attempts": 0
    },
    "full_text": "жңүдёҖдәӣmagicеӯҳеңЁеңЁжҲ‘иә«дёҠпјҢжҜ”еҰӮеҗ¬еҲ°еҖ’ж•°дјҡе°„зІҫ https://t.co/SCx7gF24Yd",
    "publish_time": "2026-05-14T00:56:05"
  },
  {
    "file_name": "HINv7WUagAAYO6C.jpg",
    "user": {
      "screen_name": "haibao0810",
      "name": "жө·е®қAlistiar"
    },
    "media_type": "images",
    "url": "https://pbs.twimg.com/media/HINv7WUagAAYO6C.jpg",
    "read_time": "2026-05-14T02:02:10",
    "is_uploaded": true,
    "upload_info": {
      "success": true,
      "message_id": 23714,
      "timestamp": "2026-05-14T02:02:13"
    },
    "is_downloaded": true,
    "download_info": {
      "success": true,
      "size": 86849,
      "size_mb": 0.08,
      "timestamp": "2026-05-14T02:02:11",
      "download_attempts": 0
    },
    "full_text": "еҮҶеӨҮйҷҚдҪҺдёҖдёӢзҡ®иҙЁйҶҮ https://t.co/UIc1aEPxQq",
    "publish_time": "2026-05-14T01:05:14"
  },
  {
    "file_name": "HINwqq8akAAS3lJ.jpg",
    "user": {
      "screen_name": "acheng21501864",
      "name": "Wave"
    },
    "media_type": "images",
    "url": "https://pbs.twimg.com/media/HINwqq8akAAS3lJ.jpg",
    "read_time": "2026-05-14T02:02:10",
    "is_uploaded": true,
    "upload_info": {
      "success": true,
      "message_id": 23715,
      "timestamp": "2026-05-14T02:02:14"
    },
    "is_downloaded": true,
    "download_info": {
      "success": true,
      "size": 61255,
      "size_mb": 0.06,
      "timestamp": "2026-05-14T02:02:13",
      "download_attempts": 0
    },
    "full_text": "е°Ҹрҹҗ¶жқҘиўӯ https://t.co/Vy4MZlMHOG",
    "publish_time": "2026-05-14T01:08:31"
  },
  {
    "file_name": "HINwqrKakAIulfu.jpg",
    "user": {
      "screen_name": "acheng21501864",
      "name": "Wave"
    },
    "media_type": "images",
    "url": "https://pbs.twimg.com/media/HINwqrKakAIulfu.jpg",
    "read_time": "2026-05-14T02:02:10",
    "is_uploaded": true,
    "upload_info": {
      "success": true,
      "message_id": 23716,
      "timestamp": "2026-05-14T02:02:16"
    },
    "is_downloaded": true,
    "download_info": {
      "success": true,
      "size": 93683,
      "size_mb": 0.09,
      "timestamp": "2026-05-14T02:02:14",
      "download_attempts": 0
    },
    "full_text": "е°Ҹрҹҗ¶жқҘиўӯ https://t.co/Vy4MZlMHOG",
    "publish_time": "2026-05-14T01:08:31"
  },
  {
    "file_name": "HINwqrdbEAAFCcr.jpg",
    "user": {
      "screen_name": "acheng21501864",
      "name": "Wave"
    },
    "media_type": "images",
    "url": "https://pbs.twimg.com/media/HINwqrdbEAAFCcr.jpg",
    "read_time": "2026-05-14T02:02:10",
    "is_uploaded": true,
    "upload_info": {
      "success": true,
      "message_id": 23717,
      "timestamp": "2026-05-14T02:02:17"
    },
    "is_downloaded": true,
    "download_info": {
      "success": true,
      "size": 54550,
      "size_mb": 0.05,
      "timestamp": "2026-05-14T02:02:16",
      "download_attempts": 0
    },
    "full_text": "е°Ҹрҹҗ¶жқҘиўӯ https://t.co/Vy4MZlMHOG",
    "publish_time": "2026-05-14T01:08:31"
  },
  {
    "file_name": "z9A-ZZvWq83VhoDw.mp4",
    "user": {
      "screen_name": "haibao0810",
      "name": "жө·е®қAlistiar"
    },
    "media_type": "videos",
    "url": "https://video.twimg.com/ext_tw_video/2054615164134289408/pu/vid/avc1/720x1280/z9A-ZZvWq83VhoDw.mp4?tag=12",
    "read_time": "2026-05-14T02:02:10",
    "is_uploaded": true,
    "upload_info": {
      "success": true,
      "message_id": 23718,
      "timestamp": "2026-05-14T02:02:21"
    },
    "is_downloaded": true,
    "download_info": {
      "success": true,
      "size": 4562662,
      "size_mb": 4.35,
      "timestamp": "2026-05-14T02:02:17",
      "download_attempts": 0
    },
    "full_text": "зҡ®иҙЁйҶҮе·ІйҷҚдҪҺпјҢдёҚиҝҮзүӣеҘ¶йғҪеј„еҲ°жҜӣжҜӣдёҠдјҡдёҚдјҡжңүзӮ№жөӘиҙ№ https://t.co/D1GEG6WaXj",
    "publish_time": "2026-05-14T01:30:12"
  },
  {
    "file_name": "HIOH0lJbcAApqyd.jpg",
    "user": {
      "screen_name": "liangguai1",
      "name": "дә®жӢҗ"
    },
    "media_type": "images",
    "url": "https://pbs.twimg.com/media/HIOH0lJbcAApqyd.jpg",
    "read_time": "2026-05-14T03:02:00",
    "is_uploaded": true,
    "upload_info": {
      "success": true,
      "message_id": 23719,
      "timestamp": "2026-05-14T03:02:02"
    },
    "is_downloaded": true,
    "download_info": {
      "success": true,
      "size": 84618,
      "size_mb": 0.08,
      "timestamp": "2026-05-14T03:02:00",
      "download_attempts": 0
    },
    "full_text": "https://t.co/B5mnIdGSIi",
    "publish_time": "2026-05-14T02:49:40"
  },
  {
    "file_name": "9Texxa6U6D-Rwdu9.mp4",
    "user": {
      "screen_name": "77baxi",
      "name": "еҒҘиә«ж•ҷз»ғcdдјӘеЁҳ"
    },
    "media_type": "videos",
    "url": "https://video.twimg.com/amplify_video/2012037669518479360/vid/avc1/1080x1080/9Texxa6U6D-Rwdu9.mp4?tag=21",
    "read_time": "2026-05-14T06:02:03",
    "is_uploaded": false,
    "upload_info": {
      "success": false,
      "error_type": "file_too_large",
      "message": "videosеӨ§е°Ҹи¶…ж Ү (131MB > 50MB)",
      "timestamp": "2026-05-14T06:02:04",
      "notification_sent": true
    },
    "is_downloaded": true,
    "download_info": {
      "success": true,
      "size": 137987600,
      "size_mb": 131.6,
      "timestamp": "2026-05-14T07:02:15",
      "download_attempts": 0
    },
    "full_text": "https://t.co/PePZMZw3EU",
    "publish_time": "2026-05-14T04:12:10"
  },
  {
    "file_name": "HIOtLuca0AAjuTi.jpg",
    "user": {
      "screen_name": "eric_kk97",
      "name": "ManFeedрҹҚҶ"
    },
    "media_type": "images",
    "url": "https://pbs.twimg.com/media/HIOtLuca0AAjuTi.jpg",
    "read_time": "2026-05-14T06:02:03",
    "is_uploaded": true,
    "upload_info": {
      "success": true,
      "message_id": 23720,
      "timestamp": "2026-05-14T06:02:06"
    },
    "is_downloaded": true,
    "download_info": {
      "success": true,
      "size": 98876,
      "size_mb": 0.09,
      "timestamp": "2026-05-14T06:02:04",
      "download_attempts": 0
    },
    "full_text": "https://t.co/9qJCdbRMrn",
    "publish_time": "2026-05-14T05:32:53"
  },
  {
    "file_name": "HIOtONdbEAAS1yM.jpg",
    "user": {
      "screen_name": "eric_kk97",
      "name": "ManFeedрҹҚҶ"
    },
    "media_type": "images",
    "url": "https://pbs.twimg.com/media/HIOtONdbEAAS1yM.jpg",
    "read_time": "2026-05-14T06:02:03",
    "is_uploaded": true,
    "upload_info": {
      "success": true,
      "message_id": 23721,
      "timestamp": "2026-05-14T06:02:07"
    },
    "is_downloaded": true,
    "download_info": {
      "success": true,
      "size": 120814,
      "size_mb": 0.12,
      "timestamp": "2026-05-14T06:02:06",
      "download_attempts": 0
    },
    "full_text": "https://t.co/9pAsTE6MHS",
    "publish_time": "2026-05-14T05:33:04"
  },
  {
    "file_name": "HIOuP56bIAA2J_i.jpg",
    "user": {
      "screen_name": "zuiaiyewan2018",
      "name": "zuiai1314"
    },
    "media_type": "images",
    "url": "https://pbs.twimg.com/media/HIOuP56bIAA2J_i.jpg",
    "read_time": "2026-05-14T06:02:03",
    "is_uploaded": true,
    "upload_info": {
      "success": true,
      "message_id": 23722,
      "timestamp": "2026-05-14T06:02:08"
    },
    "is_downloaded": true,
    "download_info": {
      "success": true,
      "size": 124379,
      "size_mb": 0.12,
      "timestamp": "2026-05-14T06:02:07",
      "download_attempts": 0
    },
    "full_text": "и·‘еӣўйҮҢзҡ„еҸ”еҸ”рҹҢё https://t.co/PYikYOVHLX",
    "publish_time": "2026-05-14T05:38:50"
  },
  {
    "file_name": "DKbMCIpI0uHli1eQ.mp4",
    "user": {
      "screen_name": "zuiaiyewan2018",
      "name": "zuiai1314"
    },
    "media_type": "videos",
    "url": "https://video.twimg.com/amplify_video/2054677444008046592/vid/avc1/720x1556/DKbMCIpI0uHli1eQ.mp4?tag=14",
    "read_time": "2026-05-14T06:02:03",
    "is_uploaded": true,
    "upload_info": {
      "success": true,
      "message_id": 23723,
      "timestamp": "2026-05-14T06:02:12"
    },
    "is_downloaded": true,
    "download_info": {
      "success": true,
      "size": 3311121,
      "size_mb": 3.16,
      "timestamp": "2026-05-14T06:02:09",
      "download_attempts": 0
    },
    "full_text": "и·‘еӣўйҮҢзҡ„еҸ”еҸ”рҹҢё https://t.co/PYikYOVHLX",
    "publish_time": "2026-05-14T05:38:50"
  },
  {
    "file_name": "HIPQjWya8AAiXGP.jpg",
    "user": {
      "screen_name": "Forestwoodwood",
      "name": "FOREST ALBUM рҹҸіпёҸвҖҚрҹҢҲ"
    },
    "media_type": "images",
    "url": "https://pbs.twimg.com/media/HIPQjWya8AAiXGP.jpg",
    "read_time": "2026-05-14T09:02:01",
    "is_uploaded": true,
    "upload_info": {
      "success": true,
      "message_id": 23724,
      "timestamp": "2026-05-14T09:02:04"
    },
    "is_downloaded": true,
    "download_info": {
      "success": true,
      "size": 164048,
      "size_mb": 0.16,
      "timestamp": "2026-05-14T09:02:02",
      "download_attempts": 0
    },
    "full_text": "В·\nрҹҺ¬ вҖңе·ҙеЈ«е…¬еӣӯвҖқзі»еҲ—д№ӢдёҖ\n\nрҹ“·вңЁж‘„еҪұеёҲHenryjiе®Ү@henryji8090\n\nрҹ‘Өрҹ’«KevinLeeYoung @KevinLeeYoung92\n. https://t.co/ixziZOE0jF",
    "publish_time": "2026-05-14T08:07:24"
  },
  {
    "file_name": "HIPQjWxbEAA2Qz3.jpg",
    "user": {
      "screen_name": "Forestwoodwood",
      "name": "FOREST ALBUM рҹҸіпёҸвҖҚрҹҢҲ"
    },
    "media_type": "images",
    "url": "https://pbs.twimg.com/media/HIPQjWxbEAA2Qz3.jpg",
    "read_time": "2026-05-14T09:02:01",
    "is_uploaded": true,
    "upload_info": {
      "success": true,
      "message_id": 23725,
      "timestamp": "2026-05-14T09:02:05"
    },
    "is_downloaded": true,
    "download_info": {
      "success": true,
      "size": 185338,
      "size_mb": 0.18,
      "timestamp": "2026-05-14T09:02:04",
      "download_attempts": 0
    },
    "full_text": "В·\nрҹҺ¬ вҖңе·ҙеЈ«е…¬еӣӯвҖқзі»еҲ—д№ӢдёҖ\n\nрҹ“·вңЁж‘„еҪұеёҲHenryjiе®Ү@henryji8090\n\nрҹ‘Өрҹ’«KevinLeeYoung @KevinLeeYoung92\n. https://t.co/ixziZOE0jF",
    "publish_time": "2026-05-14T08:07:24"
  },
  {
    "file_name": "HIPQjWxaYAAaSik.jpg",
    "user": {
      "screen_name": "Forestwoodwood",
      "name": "FOREST ALBUM рҹҸіпёҸвҖҚрҹҢҲ"
    },
    "media_type": "images",
    "url": "https://pbs.twimg.com/media/HIPQjWxaYAAaSik.jpg",
    "read_time": "2026-05-14T09:02:01",
    "is_uploaded": true,
    "upload_info": {
      "success": true,
      "message_id": 23726,
      "timestamp": "2026-05-14T09:02:07"
    },
    "is_downloaded": true,
    "download_info": {
      "success": true,
      "size": 205828,
      "size_mb": 0.2,
      "timestamp": "2026-05-14T09:02:06",
      "download_attempts": 0
    },
    "full_text": "В·\nрҹҺ¬ вҖңе·ҙеЈ«е…¬еӣӯвҖқзі»еҲ—д№ӢдёҖ\n\nрҹ“·вңЁж‘„еҪұеёҲHenryjiе®Ү@henryji8090\n\nрҹ‘Өрҹ’«KevinLeeYoung @KevinLeeYoung92\n. https://t.co/ixziZOE0jF",
    "publish_time": "2026-05-14T08:07:24"
  },
  {
    "file_name": "HIPQjWwacAA0hP8.jpg",
    "user": {
      "screen_name": "Forestwoodwood",
      "name": "FOREST ALBUM рҹҸіпёҸвҖҚрҹҢҲ"
    },
    "media_type": "images",
    "url": "https://pbs.twimg.com/media/HIPQjWwacAA0hP8.jpg",
    "read_time": "2026-05-14T09:02:01",
    "is_uploaded": true,
    "upload_info": {
      "success": true,
      "message_id": 23727,
      "timestamp": "2026-05-14T09:02:08"
    },
    "is_downloaded": true,
    "download_info": {
      "success": true,
      "size": 205476,
      "size_mb": 0.2,
      "timestamp": "2026-05-14T09:02:07",
      "download_attempts": 0
    },
    "full_text": "В·\nрҹҺ¬ вҖңе·ҙеЈ«е…¬еӣӯвҖқзі»еҲ—д№ӢдёҖ\n\nрҹ“·вңЁж‘„еҪұеёҲHenryjiе®Ү@henryji8090\n\nрҹ‘Өрҹ’«KevinLeeYoung @KevinLeeYoung92\n. https://t.co/ixziZOE0jF",
    "publish_time": "2026-05-14T08:07:24"
  },
  {
    "file_name": "HIPRocxakAARaHn.jpg",
    "user": {
      "screen_name": "Forestwoodwood",
      "name": "FOREST ALBUM рҹҸіпёҸвҖҚрҹҢҲ"
    },
    "media_type": "images",
    "url": "https://pbs.twimg.com/media/HIPRocxakAARaHn.jpg",
    "read_time": "2026-05-14T09:02:01",
    "is_uploaded": true,
    "upload_info": {
      "success": true,
      "message_id": 23728,
      "timestamp": "2026-05-14T09:02:09"
    },
    "is_downloaded": true,
    "download_info": {
      "success": true,
      "size": 312639,
      "size_mb": 0.3,
      "timestamp": "2026-05-14T09:02:08",
      "download_attempts": 0
    },
    "full_text": "В· \nгҖҗThe Double зі»еҲ—гҖ‘ TWO MEN together series SilverArtMan_ дҪңе“ҒйҖүиҪҪпҪң #NSFW AIВ·AGI-era humansи¶…жё…дјјзңҹгҖӮ SilverArtMan AGI\n@SilverArtManAGI\nд»–зҡ„зҪ‘з«ҷ https://t.co/mcrIe8VmAs https://t.co/d311y7IamO",
    "publish_time": "2026-05-14T08:13:14"
  },
  {
    "file_name": "HIPRqRpaYAAF0_M.jpg",
    "user": {
      "screen_name": "Forestwoodwood",
      "name": "FOREST ALBUM рҹҸіпёҸвҖҚрҹҢҲ"
    },
    "media_type": "images",
    "url": "https://pbs.twimg.com/media/HIPRqRpaYAAF0_M.jpg",
    "read_time": "2026-05-14T09:02:01",
    "is_uploaded": true,
    "upload_info": {
      "success": true,
      "message_id": 23729,
      "timestamp": "2026-05-14T09:02:10"
    },
    "is_downloaded": true,
    "download_info": {
      "success": true,
      "size": 147110,
      "size_mb": 0.14,
      "timestamp": "2026-05-14T09:02:09",
      "download_attempts": 0
    },
    "full_text": "В· \nгҖҗThe Double зі»еҲ—гҖ‘ TWO MEN together series SilverArtMan_ дҪңе“ҒйҖүиҪҪпҪң #NSFW AIВ·AGI-era humansи¶…жё…дјјзңҹгҖӮ SilverArtMan AGI\n@SilverArtManAGI\nд»–зҡ„зҪ‘з«ҷ https://t.co/mcrIe8VmAs https://t.co/d311y7IamO",
    "publish_time": "2026-05-14T08:13:14"
  },
  {
    "file_name": "HIPRr4SakAAOIWC.jpg",
    "user": {
      "screen_name": "Forestwoodwood",
      "name": "FOREST ALBUM рҹҸіпёҸвҖҚрҹҢҲ"
    },
    "media_type": "images",
    "url": "https://pbs.twimg.com/media/HIPRr4SakAAOIWC.jpg",
    "read_time": "2026-05-14T09:02:01",
    "is_uploaded": true,
    "upload_info": {
      "success": true,
      "message_id": 23730,
      "timestamp": "2026-05-14T09:02:11"
    },
    "is_downloaded": true,
    "download_info": {
      "success": true,
      "size": 165859,
      "size_mb": 0.16,
      "timestamp": "2026-05-14T09:02:10",
      "download_attempts": 0
    },
    "full_text": "В· \nгҖҗThe Double зі»еҲ—гҖ‘ TWO MEN together series SilverArtMan_ дҪңе“ҒйҖүиҪҪпҪң #NSFW AIВ·AGI-era humansи¶…жё…дјјзңҹгҖӮ SilverArtMan AGI\n@SilverArtManAGI\nд»–зҡ„зҪ‘з«ҷ https://t.co/mcrIe8VmAs https://t.co/d311y7IamO",
    "publish_time": "2026-05-14T08:13:14"
  },
  {
    "file_name": "HIPRs9paEAAiQVK.jpg",
    "user": {
      "screen_name": "Forestwoodwood",
      "name": "FOREST ALBUM рҹҸіпёҸвҖҚрҹҢҲ"
    },
    "media_type": "images",
    "url": "https://pbs.twimg.com/media/HIPRs9paEAAiQVK.jpg",
    "read_time": "2026-05-14T09:02:01",
    "is_uploaded": true,
    "upload_info": {
      "success": true,
      "message_id": 23731,
      "timestamp": "2026-05-14T09:02:12"
    },
    "is_downloaded": true,
    "download_info": {
      "success": true,
      "size": 352628,
      "size_mb": 0.34,
      "timestamp": "2026-05-14T09:02:11",
      "download_attempts": 0
    },
    "full_text": "В· \nгҖҗThe Double зі»еҲ—гҖ‘ TWO MEN together series SilverArtMan_ дҪңе“ҒйҖүиҪҪпҪң #NSFW AIВ·AGI-era humansи¶…жё…дјјзңҹгҖӮ SilverArtMan AGI\n@SilverArtManAGI\nд»–зҡ„зҪ‘з«ҷ https://t.co/mcrIe8VmAs https://t.co/d311y7IamO",
    "publish_time": "2026-05-14T08:13:14"
  },
  {
    "file_name": "7g0tosLirfhQMzVA.mp4",
    "user": {
      "screen_name": "bohaixiaochen",
      "name": "иҠӢжіҘеҶҚеӨҡеҠ иҠӢеңҶ"
    },
    "media_type": "videos",
    "url": "https://video.twimg.com/ext_tw_video/2054725458147840000/pu/vid/avc1/1280x720/7g0tosLirfhQMzVA.mp4?tag=12",
    "read_time": "2026-05-14T09:02:01",
    "is_uploaded": true,
    "upload_info": {
      "success": true,
      "message_id": 23732,
      "timestamp": "2026-05-14T09:02:15"
    },
    "is_downloaded": true,
    "download_info": {
      "success": true,
      "size": 294545,
      "size_mb": 0.28,
      "timestamp": "2026-05-14T09:02:13",
      "download_attempts": 0
    },
    "full_text": "жҷЁеӢғж—©ж—© https://t.co/tH6GbsXysr",
    "publish_time": "2026-05-14T08:48:31"
  },
  {
    "file_name": "hItWIu16JAfK_Aw-.mp4",
    "user": {
      "screen_name": "bohaixiaochen",
      "name": "иҠӢжіҘеҶҚеӨҡеҠ иҠӢеңҶ"
    },
    "media_type": "videos",
    "url": "https://video.twimg.com/ext_tw_video/2054725488967630848/pu/vid/avc1/1280x720/hItWIu16JAfK_Aw-.mp4?tag=12",
    "read_time": "2026-05-14T09:02:01",
    "is_uploaded": true,
    "upload_info": {
      "success": true,
      "message_id": 23733,
      "timestamp": "2026-05-14T09:02:16"
    },
    "is_downloaded": true,
    "download_info": {
      "success": true,
      "size": 312417,
      "size_mb": 0.3,
      "timestamp": "2026-05-14T09:02:15",
      "download_attempts": 0
    },
    "full_text": "жҷЁеӢғж—©ж—© https://t.co/tH6GbsXysr",
    "publish_time": "2026-05-14T08:48:31"
  },
  {
    "file_name": "L3O4Ia8BQPavfXEe.mp4",
    "user": {
      "screen_name": "Forestwoodwood",
      "name": "FOREST ALBUM рҹҸіпёҸвҖҚрҹҢҲ"
    },
    "media_type": "videos",
    "url": "https://video.twimg.com/amplify_video/2047451960664850432/vid/avc1/854x480/L3O4Ia8BQPavfXEe.mp4?tag=14",
    "read_time": "2026-05-14T09:02:01",
    "is_uploaded": true,
    "upload_info": {
      "success": true,
      "message_id": 23734,
      "timestamp": "2026-05-14T09:02:22"
    },
    "is_downloaded": true,
    "download_info": {
      "success": true,
      "size": 22242546,
      "size_mb": 21.21,
      "timestamp": "2026-05-14T09:02:19",
      "download_attempts": 0
    },
    "full_text": "В·\nрҹ”һtattooеё…е“ҘпјҡDavon @JustDavonLee https://t.co/BuYRRelBUi",
    "publish_time": "2026-05-14T08:51:26"
  },
  {
    "file_name": "HIPbj0JaMAAiK1x.jpg",
    "user": {
      "screen_name": "Forestwoodwood",
      "name": "FOREST ALBUM рҹҸіпёҸвҖҚрҹҢҲ"
    },
    "media_type": "images",
    "url": "https://pbs.twimg.com/media/HIPbj0JaMAAiK1x.jpg",
    "read_time": "2026-05-14T09:02:01",
    "is_uploaded": true,
    "upload_info": {
      "success": true,
      "message_id": 23735,
      "timestamp": "2026-05-14T09:02:22"
    },
    "is_downloaded": true,
    "download_info": {
      "success": true,
      "size": 102327,
      "size_mb": 0.1,
      "timestamp": "2026-05-14T09:02:22",
      "download_attempts": 0
    },
    "full_text": "В·\nгҖҗз»§з»ӯд»Ӣз»Қж–°з”ҹдёҖд»Ј Gen Z ж‘„еҪұеёҲ е’ҢжЁЎзү№зҡ„дҪңе“ҒгҖ‘\n\nрҹ“·е…°еҮҜ д»–зҡ„IGпјҡhessenstudioart \nрҹ“Қж·ұеңіВ·е№ҝдёң\nз”·жЁЎ IG: cq.stars.l пҪңGoGo-Dancer \nрҹ“ҚйҮҚеәҶВ·еӣӣе·қ https://t.co/kOn3DfVtU2",
    "publish_time": "2026-05-14T08:55:30"
  },
  {
    "file_name": "HIPbj0HbwAAx6Im.jpg",
    "user": {
      "screen_name": "Forestwoodwood",
      "name": "FOREST ALBUM рҹҸіпёҸвҖҚрҹҢҲ"
    },
    "media_type": "images",
    "url": "https://pbs.twimg.com/media/HIPbj0HbwAAx6Im.jpg",
    "read_time": "2026-05-14T09:02:01",
    "is_uploaded": true,
    "upload_info": {
      "success": true,
      "message_id": 23736,
      "timestamp": "2026-05-14T09:02:23"
    },
    "is_downloaded": true,
    "download_info": {
      "success": true,
      "size": 100318,
      "size_mb": 0.1,
      "timestamp": "2026-05-14T09:02:22",
      "download_attempts": 0
    },
    "full_text": "В·\nгҖҗз»§з»ӯд»Ӣз»Қж–°з”ҹдёҖд»Ј Gen Z ж‘„еҪұеёҲ е’ҢжЁЎзү№зҡ„дҪңе“ҒгҖ‘\n\nрҹ“·е…°еҮҜ д»–зҡ„IGпјҡhessenstudioart \nрҹ“Қж·ұеңіВ·е№ҝдёң\nз”·жЁЎ IG: cq.stars.l пҪңGoGo-Dancer \nрҹ“ҚйҮҚеәҶВ·еӣӣе·қ https://t.co/kOn3DfVtU2",
    "publish_time": "2026-05-14T08:55:30"
  },
  {
    "file_name": "HIPbj0HakAANy8L.jpg",
    "user": {
      "screen_name": "Forestwoodwood",
      "name": "FOREST ALBUM рҹҸіпёҸвҖҚрҹҢҲ"
    },
    "media_type": "images",
    "url": "https://pbs.twimg.com/media/HIPbj0HakAANy8L.jpg",
    "read_time": "2026-05-14T09:02:01",
    "is_uploaded": true,
    "upload_info": {
      "success": true,
      "message_id": 23737,
      "timestamp": "2026-05-14T09:02:24"
    },
    "is_downloaded": true,
    "download_info": {
      "success": true,
      "size": 94055,
      "size_mb": 0.09,
      "timestamp": "2026-05-14T09:02:23",
      "download_attempts": 0
    },
    "full_text": "В·\nгҖҗз»§з»ӯд»Ӣз»Қж–°з”ҹдёҖд»Ј Gen Z ж‘„еҪұеёҲ е’ҢжЁЎзү№зҡ„дҪңе“ҒгҖ‘\n\nрҹ“·е…°еҮҜ д»–зҡ„IGпјҡhessenstudioart \nрҹ“Қж·ұеңіВ·е№ҝдёң\nз”·жЁЎ IG: cq.stars.l пҪңGoGo-Dancer \nрҹ“ҚйҮҚеәҶВ·еӣӣе·қ https://t.co/kOn3DfVtU2",
    "publish_time": "2026-05-14T08:55:30"
  },
  {
    "file_name": "HIPbj0Mb0AAeXsK.jpg",
    "user": {
      "screen_name": "Forestwoodwood",
      "name": "FOREST ALBUM рҹҸіпёҸвҖҚрҹҢҲ"
    },
    "media_type": "images",
    "url": "https://pbs.twimg.com/media/HIPbj0Mb0AAeXsK.jpg",
    "read_time": "2026-05-14T09:02:01",
    "is_uploaded": true,
    "upload_info": {
      "success": true,
      "message_id": 23738,
      "timestamp": "2026-05-14T09:02:24"
    },
    "is_downloaded": true,
    "download_info": {
      "success": true,
      "size": 103396,
      "size_mb": 0.1,
      "timestamp": "2026-05-14T09:02:24",
      "download_attempts": 0
    },
    "full_text": "В·\nгҖҗз»§з»ӯд»Ӣз»Қж–°з”ҹдёҖд»Ј Gen Z ж‘„еҪұеёҲ е’ҢжЁЎзү№зҡ„дҪңе“ҒгҖ‘\n\nрҹ“·е…°еҮҜ д»–зҡ„IGпјҡhessenstudioart \nрҹ“Қж·ұеңіВ·е№ҝдёң\nз”·жЁЎ IG: cq.stars.l пҪңGoGo-Dancer \nрҹ“ҚйҮҚеәҶВ·еӣӣе·қ https://t.co/kOn3DfVtU2",
    "publish_time": "2026-05-14T08:55:30"
  },
  {
    "file_name": "HIPbw_5b0AAYmpF.jpg",
    "user": {
      "screen_name": "Forestwoodwood",
      "name": "FOREST ALBUM рҹҸіпёҸвҖҚрҹҢҲ"
    },
    "media_type": "images",
    "url": "https://pbs.twimg.com/media/HIPbw_5b0AAYmpF.jpg",
    "read_time": "2026-05-14T09:02:01",
    "is_uploaded": true,
    "upload_info": {
      "success": true,
      "message_id": 23739,
      "timestamp": "2026-05-14T09:02:25"
    },
    "is_downloaded": true,
    "download_info": {
      "success": true,
      "size": 81858,
      "size_mb": 0.08,
      "timestamp": "2026-05-14T09:02:24",
      "download_attempts": 0
    },
    "full_text": "https://t.co/ut4NJ6aeAt",
    "publish_time": "2026-05-14T08:56:24"
  },
  {
    "file_name": "HIPbw_6b0AAeJgr.jpg",
    "user": {
      "screen_name": "Forestwoodwood",
      "name": "FOREST ALBUM рҹҸіпёҸвҖҚрҹҢҲ"
    },
    "media_type": "images",
    "url": "https://pbs.twimg.com/media/HIPbw_6b0AAeJgr.jpg",
    "read_time": "2026-05-14T09:02:01",
    "is_uploaded": true,
    "upload_info": {
      "success": true,
      "message_id": 23740,
      "timestamp": "2026-05-14T09:02:26"
    },
    "is_downloaded": true,
    "download_info": {
      "success": true,
      "size": 90572,
      "size_mb": 0.09,
      "timestamp": "2026-05-14T09:02:25",
      "download_attempts": 0
    },
    "full_text": "https://t.co/ut4NJ6aeAt",
    "publish_time": "2026-05-14T08:56:24"
  },
  {
    "file_name": "HIPbw_3bsAAwlyX.jpg",
    "user": {
      "screen_name": "Forestwoodwood",
      "name": "FOREST ALBUM рҹҸіпёҸвҖҚрҹҢҲ"
    },
    "media_type": "images",
    "url": "https://pbs.twimg.com/media/HIPbw_3bsAAwlyX.jpg",
    "read_time": "2026-05-14T09:02:01",
    "is_uploaded": true,
    "upload_info": {
      "success": true,
      "message_id": 23741,
      "timestamp": "2026-05-14T09:02:26"
    },
    "is_downloaded": true,
    "download_info": {
      "success": true,
      "size": 94977,
      "size_mb": 0.09,
      "timestamp": "2026-05-14T09:02:26",
      "download_attempts": 0
    },
    "full_text": "https://t.co/ut4NJ6aeAt",
    "publish_time": "2026-05-14T08:56:24"
  },
  {
    "file_name": "HIPbw_3bwAAPsnd.jpg",
    "user": {
      "screen_name": "Forestwoodwood",
      "name": "FOREST ALBUM рҹҸіпёҸвҖҚрҹҢҲ"
    },
    "media_type": "images",
    "url": "https://pbs.twimg.com/media/HIPbw_3bwAAPsnd.jpg",
    "read_time": "2026-05-14T09:02:01",
    "is_uploaded": true,
    "upload_info": {
      "success": true,
      "message_id": 23742,
      "timestamp": "2026-05-14T09:02:27"
    },
    "is_downloaded": true,
    "download_info": {
      "success": true,
      "size": 86975,
      "size_mb": 0.08,
      "timestamp": "2026-05-14T09:02:26",
      "download_attempts": 0
    },
    "full_text": "https://t.co/ut4NJ6aeAt",
    "publish_time": "2026-05-14T08:56:24"
  },
  {
    "file_name": "vRzcSBTnAuXtxF6R.mp4",
    "user": {
      "screen_name": "Forestwoodwood",
      "name": "FOREST ALBUM рҹҸіпёҸвҖҚрҹҢҲ"
    },
    "media_type": "videos",
    "url": "https://video.twimg.com/amplify_video/2054730540050472960/vid/avc1/1080x1536/vRzcSBTnAuXtxF6R.mp4?tag=27",
    "read_time": "2026-05-14T10:02:15",
    "is_uploaded": true,
    "upload_info": {
      "success": true,
      "message_id": 23743,
      "timestamp": "2026-05-14T10:02:21"
    },
    "is_downloaded": true,
    "download_info": {
      "success": true,
      "size": 9771562,
      "size_mb": 9.32,
      "timestamp": "2026-05-14T10:02:16",
      "download_attempts": 0
    },
    "full_text": "В·\nCircleеӨ§жәҗ  * rednote ID: 605326835 рҹ“Қ дёҠе‘Ёжң«еңЁж·ұеңіmusclemaniaеҒҘзҫҺеӨ§иөӣдёҠиҺ·еҚ•йЎ№е’Ңе…ЁеңәеҶ еҶӣрҹҸҶпҪңд»–жӯЈеңЁдёәеҺ»зҫҺеӣҪз•ҷеӯҰз”ҹжҙ»еҮҶеӨҮрҹ’Ұрҹ’Ұрҹ’Ұ https://t.co/YqNq53UDky",
    "publish_time": "2026-05-14T09:08:55"
  },
  {
    "file_name": "HIPihwNaIAAN7R3.jpg",
    "user": {
      "screen_name": "KingKongnb",
      "name": "дё¶ж–°дёҖиҖҒеёҲ"
    },
    "media_type": "images",
    "url": "https://pbs.twimg.com/media/HIPihwNaIAAN7R3.jpg",
    "read_time": "2026-05-14T10:02:15",
    "is_uploaded": true,
    "upload_info": {
      "success": true,
      "message_id": 23744,
      "timestamp": "2026-05-14T10:02:22"
    },
    "is_downloaded": true,
    "download_info": {
      "success": true,
      "size": 113333,
      "size_mb": 0.11,
      "timestamp": "2026-05-14T10:02:21",
      "download_attempts": 0
    },
    "full_text": "ж—© https://t.co/VdeDkqhGIo",
    "publish_time": "2026-05-14T09:26:00"
  },
  {
    "file_name": "HIPjb-xbIAA7yQN.jpg",
    "user": {
      "screen_name": "BLPDBNANA",
      "name": "Mr.CumBoYрҹҚҢ"
    },
    "media_type": "images",
    "url": "https://pbs.twimg.com/media/HIPjb-xbIAA7yQN.jpg",
    "read_time": "2026-05-14T10:02:15",
    "is_uploaded": true,
    "upload_info": {
      "success": true,
      "message_id": 23745,
      "timestamp": "2026-05-14T10:02:23"
    },
    "is_downloaded": true,
    "download_info": {
      "success": true,
      "size": 73475,
      "size_mb": 0.07,
      "timestamp": "2026-05-14T10:02:22",
      "download_attempts": 0
    },
    "full_text": "зҰ»иҖғиҜ•иҝҳжңүдёүеӨ©\nжҲ‘еҸҲжқҘиҮӘд№ е®Ө\nзӘҒз„¶жңүдёҖдёӘеқҸдё»ж„Ҹ\nжғіе®ҡдёҖй—ҙеҸҢдәәеҢ…й—ҙ\nжүҫдёҖдёӘжқҜеҸӢ\nеёҰдёҠеҗ„иҮӘзҡ„йЈһжңәжқҜ\nеӯҰд№ еҰӮдҪ•ж”№е–„ж—©жі„\nиҪ»еЈ°дәӨвҖңжөҒвҖқ https://t.co/oGFjtiHegF",
    "publish_time": "2026-05-14T09:29:58"
  },
  {
    "file_name": "HIPjb-yaEAEfxW5.jpg",
    "user": {
      "screen_name": "BLPDBNANA",
      "name": "Mr.CumBoYрҹҚҢ"
    },
    "media_type": "images",
    "url": "https://pbs.twimg.com/media/HIPjb-yaEAEfxW5.jpg",
    "read_time": "2026-05-14T10:02:15",
    "is_uploaded": true,
    "upload_info": {
      "success": true,
      "message_id": 23746,
      "timestamp": "2026-05-14T10:02:24"
    },
    "is_downloaded": true,
    "download_info": {
      "success": true,
      "size": 82612,
      "size_mb": 0.08,
      "timestamp": "2026-05-14T10:02:23",
      "download_attempts": 0
    },
    "full_text": "зҰ»иҖғиҜ•иҝҳжңүдёүеӨ©\nжҲ‘еҸҲжқҘиҮӘд№ е®Ө\nзӘҒз„¶жңүдёҖдёӘеқҸдё»ж„Ҹ\nжғіе®ҡдёҖй—ҙеҸҢдәәеҢ…й—ҙ\nжүҫдёҖдёӘжқҜеҸӢ\nеёҰдёҠеҗ„иҮӘзҡ„йЈһжңәжқҜ\nеӯҰд№ еҰӮдҪ•ж”№е–„ж—©жі„\nиҪ»еЈ°дәӨвҖңжөҒвҖқ https://t.co/oGFjtiHegF",
    "publish_time": "2026-05-14T09:29:58"
  },
  {
    "file_name": "HIPjb-yacAAHIkF.jpg",
    "user": {
      "screen_name": "BLPDBNANA",
      "name": "Mr.CumBoYрҹҚҢ"
    },
    "media_type": "images",
    "url": "https://pbs.twimg.com/media/HIPjb-yacAAHIkF.jpg",
    "read_time": "2026-05-14T10:02:15",
    "is_uploaded": true,
    "upload_info": {
      "success": true,
      "message_id": 23747,
      "timestamp": "2026-05-14T10:02:24"
    },
    "is_downloaded": true,
    "download_info": {
      "success": true,
      "size": 90186,
      "size_mb": 0.09,
      "timestamp": "2026-05-14T10:02:24",
      "download_attempts": 0
    },
    "full_text": "зҰ»иҖғиҜ•иҝҳжңүдёүеӨ©\nжҲ‘еҸҲжқҘиҮӘд№ е®Ө\nзӘҒз„¶жңүдёҖдёӘеқҸдё»ж„Ҹ\nжғіе®ҡдёҖй—ҙеҸҢдәәеҢ…й—ҙ\nжүҫдёҖдёӘжқҜеҸӢ\nеёҰдёҠеҗ„иҮӘзҡ„йЈһжңәжқҜ\nеӯҰд№ еҰӮдҪ•ж”№е–„ж—©жі„\nиҪ»еЈ°дәӨвҖңжөҒвҖқ https://t.co/oGFjtiHegF",
    "publish_time": "2026-05-14T09:29:58"
  },
  {
    "file_name": "HIPjb-zboAAnDtj.jpg",
    "user": {
      "screen_name": "BLPDBNANA",
      "name": "Mr.CumBoYрҹҚҢ"
    },
    "media_type": "images",
    "url": "https://pbs.twimg.com/media/HIPjb-zboAAnDtj.jpg",
    "read_time": "2026-05-14T10:02:15",
    "is_uploaded": true,
    "upload_info": {
      "success": true,
      "message_id": 23748,
      "timestamp": "2026-05-14T10:02:25"
    },
    "is_downloaded": true,
    "download_info": {
      "success": true,
      "size": 245108,
      "size_mb": 0.23,
      "timestamp": "2026-05-14T10:02:25",
      "download_attempts": 0
    },
    "full_text": "зҰ»иҖғиҜ•иҝҳжңүдёүеӨ©\nжҲ‘еҸҲжқҘиҮӘд№ е®Ө\nзӘҒз„¶жңүдёҖдёӘеқҸдё»ж„Ҹ\nжғіе®ҡдёҖй—ҙеҸҢдәәеҢ…й—ҙ\nжүҫдёҖдёӘжқҜеҸӢ\nеёҰдёҠеҗ„иҮӘзҡ„йЈһжңәжқҜ\nеӯҰд№ еҰӮдҪ•ж”№е–„ж—©жі„\nиҪ»еЈ°дәӨвҖңжөҒвҖқ https://t.co/oGFjtiHegF",
    "publish_time": "2026-05-14T09:29:58"
  },
  {
    "file_name": "HIPjqDXacAAas1U.jpg",
    "user": {
      "screen_name": "markma58304799",
      "name": "MARK.xiaohui"
    },
    "media_type": "images",
    "url": "https://pbs.twimg.com/media/HIPjqDXacAAas1U.jpg",
    "read_time": "2026-05-14T10:02:15",
    "is_uploaded": true,
    "upload_info": {
      "success": true,
      "message_id": 23749,
      "timestamp": "2026-05-14T10:02:26"
    },
    "is_downloaded": true,
    "download_info": {
      "success": true,
      "size": 124381,
      "size_mb": 0.12,
      "timestamp": "2026-05-14T10:02:25",
      "download_attempts": 0
    },
    "full_text": "рҹ’ӣ https://t.co/ZA654THW3O",
    "publish_time": "2026-05-14T09:30:55"
  },
  {
    "file_name": "HIPjqDYbUAAjzwR.jpg",
    "user": {
      "screen_name": "markma58304799",
      "name": "MARK.xiaohui"
    },
    "media_type": "images",
    "url": "https://pbs.twimg.com/media/HIPjqDYbUAAjzwR.jpg",
    "read_time": "2026-05-14T10:02:15",
    "is_uploaded": true,
    "upload_info": {
      "success": true,
      "message_id": 23750,
      "timestamp": "2026-05-14T10:02:27"
    },
    "is_downloaded": true,
    "download_info": {
      "success": true,
      "size": 118724,
      "size_mb": 0.11,
      "timestamp": "2026-05-14T10:02:26",
      "download_attempts": 0
    },
    "full_text": "рҹ’ӣ https://t.co/ZA654THW3O",
    "publish_time": "2026-05-14T09:30:55"
  },
  {
    "file_name": "HIPjsPLbAAAS36w.jpg",
    "user": {
      "screen_name": "quebaner16598",
      "name": "quebaner"
    },
    "media_type": "images",
    "url": "https://pbs.twimg.com/media/HIPjsPLbAAAS36w.jpg",
    "read_time": "2026-05-14T10:02:15",
    "is_uploaded": true,
    "upload_info": {
      "success": true,
      "message_id": 23751,
      "timestamp": "2026-05-14T10:02:28"
    },
    "is_downloaded": true,
    "download_info": {
      "success": true,
      "size": 190494,
      "size_mb": 0.18,
      "timestamp": "2026-05-14T10:02:27",
      "download_attempts": 0
    },
    "full_text": "рҹ‘җрҹҸ» https://t.co/DwMXpneKE9",
    "publish_time": "2026-05-14T09:31:03"
  },
  {
    "file_name": "HIPjsOSaEAAp2i4.jpg",
    "user": {
      "screen_name": "quebaner16598",
      "name": "quebaner"
    },
    "media_type": "images",
    "url": "https://pbs.twimg.com/media/HIPjsOSaEAAp2i4.jpg",
    "read_time": "2026-05-14T10:02:15",
    "is_uploaded": true,
    "upload_info": {
      "success": true,
      "message_id": 23752,
      "timestamp": "2026-05-14T10:02:28"
    },
    "is_downloaded": true,
    "download_info": {
      "success": true,
      "size": 169938,
      "size_mb": 0.16,
      "timestamp": "2026-05-14T10:02:28",
      "download_attempts": 0
    },
    "full_text": "рҹ‘җрҹҸ» https://t.co/DwMXpneKE9",
    "publish_time": "2026-05-14T09:31:03"
  },
  {
    "file_name": "HIPjsORaUAAocXM.jpg",
    "user": {
      "screen_name": "quebaner16598",
      "name": "quebaner"
    },
    "media_type": "images",
    "url": "https://pbs.twimg.com/media/HIPjsORaUAAocXM.jpg",
    "read_time": "2026-05-14T10:02:15",
    "is_uploaded": true,
    "upload_info": {
      "success": true,
      "message_id": 23753,
      "timestamp": "2026-05-14T10:02:29"
    },
    "is_downloaded": true,
    "download_info": {
      "success": true,
      "size": 152754,
      "size_mb": 0.15,
      "timestamp": "2026-05-14T10:02:29",
      "download_attempts": 0
    },
    "full_text": "рҹ‘җрҹҸ» https://t.co/DwMXpneKE9",
    "publish_time": "2026-05-14T09:31:03"
  },
  {
    "file_name": "rR_jrrDsNpOgwDmK.mp4",
    "user": {
      "screen_name": "sx84604818",
      "name": "Rexsonic Man+ suits & socks"
    },
    "media_type": "videos",
    "url": "https://video.twimg.com/amplify_video/2054742568903331840/vid/avc1/720x1280/rR_jrrDsNpOgwDmK.mp4?tag=27",
    "read_time": "2026-05-14T10:02:15",
    "is_uploaded": true,
    "upload_info": {
      "success": true,
      "message_id": 23754,
      "timestamp": "2026-05-14T10:02:33"
    },
    "is_downloaded": true,
    "download_info": {
      "success": true,
      "size": 1610179,
      "size_mb": 1.54,
      "timestamp": "2026-05-14T10:02:31",
      "download_attempts": 0
    },
    "full_text": "рҹ‘”иҘҝиЈқж„ӣеҘҪиҖ…рҹ‘” https://t.co/NOYMeMLbHN",
    "publish_time": "2026-05-14T09:56:24"
  },
  {
    "file_name": "CzfRYvAUeTW_0Vq5.mp4",
    "user": {
      "screen_name": "BBoy1069",
      "name": "жҲ‘жҳҜиҮӯзӣҙз”·"
    },
    "media_type": "videos",
    "url": "https://video.twimg.com/amplify_video/2054752205652230144/vid/avc1/720x1280/CzfRYvAUeTW_0Vq5.mp4?tag=14",
    "read_time": "2026-05-14T11:02:01",
    "is_uploaded": true,
    "upload_info": {
      "success": true,
      "message_id": 23755,
      "timestamp": "2026-05-14T11:02:05"
    },
    "is_downloaded": true,
    "download_info": {
      "success": true,
      "size": 2221127,
      "size_mb": 2.12,
      "timestamp": "2026-05-14T11:02:02",
      "download_attempts": 0
    },
    "full_text": "гҖҗ2026е№ҙ5жңҲ14ж—ҘгҖ‘д»Ҡж—ҘиіҮжәҗе·Із¶“жӣҙж–°пјҒд»ҘдёӢиҰ–й »иҲҮжӣҙж–°иіҮжәҗз„Ўй—ңпјҒ https://t.co/0rjOUwzYNg",
    "publish_time": "2026-05-14T10:34:48"
  },
  {
    "file_name": "HIQCogwaYAAg7d8.jpg",
    "user": {
      "screen_name": "CFuimaono82031",
      "name": "Cynthia Fuimaono"
    },
    "media_type": "images",
    "url": "https://pbs.twimg.com/media/HIQCogwaYAAg7d8.jpg",
    "read_time": "2026-05-14T12:01:55",
    "is_uploaded": true,
    "upload_info": {
      "success": true,
      "message_id": 23756,
      "timestamp": "2026-05-14T12:01:58"
    },
    "is_downloaded": true,
    "download_info": {
      "success": true,
      "size": 39772,
      "size_mb": 0.04,
      "timestamp": "2026-05-14T12:01:56",
      "download_attempts": 0
    },
    "full_text": "еӣӣе·қ185дҪ“иӮІиҖҒеёҲжҺ°иҸҠеҪ“рҹҗ¶иҮӘжёҺйЈһжңәжҖ’е°„ https://t.co/YRbkMrTvSD",
    "publish_time": "2026-05-14T11:46:40"
  },
  {
    "file_name": "ynEy14doJOzGBoA0.mp4",
    "user": {
      "screen_name": "CFuimaono82031",
      "name": "Cynthia Fuimaono"
    },
    "media_type": "videos",
    "url": "https://video.twimg.com/amplify_video/2054770225040781312/vid/avc1/720x1280/ynEy14doJOzGBoA0.mp4?tag=14",
    "read_time": "2026-05-14T12:01:55",
    "is_uploaded": true,
    "upload_info": {
      "success": true,
      "message_id": 23757,
      "timestamp": "2026-05-14T12:02:00"
    },
    "is_downloaded": true,
    "download_info": {
      "success": true,
      "size": 2481089,
      "size_mb": 2.37,
      "timestamp": "2026-05-14T12:01:58",
      "download_attempts": 0
    },
    "full_text": "еӣӣе·қ185дҪ“иӮІиҖҒеёҲжҺ°иҸҠеҪ“рҹҗ¶иҮӘжёҺйЈһжңәжҖ’е°„ https://t.co/YRbkMrTvSD",
    "publish_time": "2026-05-14T11:46:40"
  },
  {
    "file_name": "g4mRio2LjEpxH4di.mp4",
    "user": {
      "screen_name": "CFuimaono82031",
      "name": "Cynthia Fuimaono"
    },
    "media_type": "videos",
    "url": "https://video.twimg.com/amplify_video/2054770225015627776/vid/avc1/720x960/g4mRio2LjEpxH4di.mp4?tag=14",
    "read_time": "2026-05-14T12:01:55",
    "is_uploaded": true,
    "upload_info": {
      "success": true,
      "message_id": 23758,
      "timestamp": "2026-05-14T12:02:03"
    },
    "is_downloaded": true,
    "download_info": {
      "success": true,
      "size": 4896970,
      "size_mb": 4.67,
      "timestamp": "2026-05-14T12:02:01",
      "download_attempts": 0
    },
    "full_text": "еӣӣе·қ185дҪ“иӮІиҖҒеёҲжҺ°иҸҠеҪ“рҹҗ¶иҮӘжёҺйЈһжңәжҖ’е°„ https://t.co/YRbkMrTvSD",
    "publish_time": "2026-05-14T11:46:40"
  },
  {
    "file_name": "vct5iE5FFru80nDC.mp4",
    "user": {
      "screen_name": "CFuimaono82031",
      "name": "Cynthia Fuimaono"
    },
    "media_type": "videos",
    "url": "https://video.twimg.com/amplify_video/2054770225032417280/vid/avc1/544x960/vct5iE5FFru80nDC.mp4?tag=14",
    "read_time": "2026-05-14T12:01:55",
    "is_uploaded": true,
    "upload_info": {
      "success": true,
      "message_id": 23759,
      "timestamp": "2026-05-14T12:02:04"
    },
    "is_downloaded": true,
    "download_info": {
      "success": true,
      "size": 1483273,
      "size_mb": 1.41,
      "timestamp": "2026-05-14T12:02:03",
      "download_attempts": 0
    },
    "full_text": "еӣӣе·қ185дҪ“иӮІиҖҒеёҲжҺ°иҸҠеҪ“рҹҗ¶иҮӘжёҺйЈһжңәжҖ’е°„ https://t.co/YRbkMrTvSD",
    "publish_time": "2026-05-14T11:46:40"
  },
  {
    "file_name": "HIQKaHVbgAEit04.jpg",
    "user": {
      "screen_name": "Jeff07751908",
      "name": "е·ЁйҫҷдёҚиҜҘиў«жқҹзјҡ"
    },
    "media_type": "images",
    "url": "https://pbs.twimg.com/media/HIQKaHVbgAEit04.jpg",
    "read_time": "2026-05-14T13:01:56",
    "is_uploaded": true,
    "upload_info": {
      "success": true,
      "message_id": 23760,
      "timestamp": "2026-05-14T13:01:59"
    },
    "is_downloaded": true,
    "download_info": {
      "success": true,
      "size": 74066,
      "size_mb": 0.07,
      "timestamp": "2026-05-14T13:01:57",
      "download_attempts": 0
    },
    "full_text": "жҲҗйғҪе“ӘйҮҢжңүеӨ©дҪ“зҡ„ең°ж–№рҹҷӢ https://t.co/ALdD0OVziy",
    "publish_time": "2026-05-14T12:20:13"
  },
  {
    "file_name": "HIQKaHWbcAA1OZ9.jpg",
    "user": {
      "screen_name": "Jeff07751908",
      "name": "е·ЁйҫҷдёҚиҜҘиў«жқҹзјҡ"
    },
    "media_type": "images",
    "url": "https://pbs.twimg.com/media/HIQKaHWbcAA1OZ9.jpg",
    "read_time": "2026-05-14T13:01:56",
    "is_uploaded": true,
    "upload_info": {
      "success": true,
      "message_id": 23761,
      "timestamp": "2026-05-14T13:02:00"
    },
    "is_downloaded": true,
    "download_info": {
      "success": true,
      "size": 106170,
      "size_mb": 0.1,
      "timestamp": "2026-05-14T13:01:59",
      "download_attempts": 0
    },
    "full_text": "жҲҗйғҪе“ӘйҮҢжңүеӨ©дҪ“зҡ„ең°ж–№рҹҷӢ https://t.co/ALdD0OVziy",
    "publish_time": "2026-05-14T12:20:13"
  },
  {
    "file_name": "I-JsQCzCjyV07DW0.mp4",
    "user": {
      "screen_name": "Azrael64300",
      "name": "и–…еЈ•еҘҪжҳҠ"
    },
    "media_type": "videos",
    "url": "https://video.twimg.com/amplify_video/2053492071831588864/vid/avc1/720x1258/I-JsQCzCjyV07DW0.mp4?tag=27",
    "read_time": "2026-05-14T13:01:56",
    "is_uploaded": true,
    "upload_info": {
      "success": true,
      "message_id": 23762,
      "timestamp": "2026-05-14T13:02:05"
    },
    "is_downloaded": true,
    "download_info": {
      "success": true,
      "size": 19558696,
      "size_mb": 18.65,
      "timestamp": "2026-05-14T13:02:01",
      "download_attempts": 0
    },
    "full_text": "https://t.co/VK3wggKm5A",
    "publish_time": "2026-05-14T12:50:40"
  },
  {
    "file_name": "RQSYiTboyNv7S8BX.mp4",
    "user": {
      "screen_name": "Azrael64300",
      "name": "и–…еЈ•еҘҪжҳҠ"
    },
    "media_type": "videos",
    "url": "https://video.twimg.com/amplify_video/2054512608326418432/vid/avc1/720x1278/RQSYiTboyNv7S8BX.mp4?tag=27",
    "read_time": "2026-05-14T13:01:56",
    "is_uploaded": true,
    "upload_info": {
      "success": true,
      "message_id": 23763,
      "timestamp": "2026-05-14T13:02:08"
    },
    "is_downloaded": true,
    "download_info": {
      "success": true,
      "size": 10679739,
      "size_mb": 10.18,
      "timestamp": "2026-05-14T13:02:05",
      "download_attempts": 0
    },
    "full_text": "https://t.co/BOBs2Rrc1d",
    "publish_time": "2026-05-14T12:51:48"
  },
  {
    "file_name": "EOCTfOmHbPCLMH16.mp4",
    "user": {
      "screen_name": "Azrael64300",
      "name": "и–…еЈ•еҘҪжҳҠ"
    },
    "media_type": "videos",
    "url": "https://video.twimg.com/amplify_video/2053932979953844224/vid/avc1/720x1280/EOCTfOmHbPCLMH16.mp4?tag=27",
    "read_time": "2026-05-14T13:01:56",
    "is_uploaded": false,
    "upload_info": {
      "success": false,
      "error_type": "file_too_large",
      "message": "videosеӨ§е°Ҹи¶…ж Ү (87MB > 50MB)",
      "timestamp": "2026-05-14T13:02:08",
      "notification_sent": true
    },
    "is_downloaded": true,
    "download_info": {
      "success": true,
      "size": 92242084,
      "size_mb": 87.97,
      "timestamp": "2026-05-14T14:01:53",
      "download_attempts": 0
    },
    "full_text": "https://t.co/7W4owlkL7N",
    "publish_time": "2026-05-14T12:55:34"
  },
  {
    "file_name": "ykjrLmMdZvTHOlEE.mp4",
    "user": {
      "screen_name": "Azrael64300",
      "name": "и–…еЈ•еҘҪжҳҠ"
    },
    "media_type": "videos",
    "url": "https://video.twimg.com/ext_tw_video/2052636757343240192/pu/vid/avc1/720x1266/ykjrLmMdZvTHOlEE.mp4?tag=12",
    "read_time": "2026-05-14T13:01:56",
    "is_uploaded": true,
    "upload_info": {
      "success": true,
      "message_id": 23764,
      "timestamp": "2026-05-14T13:02:10"
    },
    "is_downloaded": true,
    "download_info": {
      "success": true,
      "size": 14860400,
      "size_mb": 14.17,
      "timestamp": "2026-05-14T13:02:08",
      "download_attempts": 0
    },
    "full_text": "https://t.co/Dj2v3dNgTe",
    "publish_time": "2026-05-14T12:58:19"
  },
  {
    "file_name": "PzkaFSoXSLG-dijx.mp4",
    "user": {
      "screen_name": "pfejui",
      "name": "е•Ҡиҝҷзӣҙз”·"
    },
    "media_type": "videos",
    "url": "https://video.twimg.com/amplify_video/2054790196856860672/vid/avc1/720x918/PzkaFSoXSLG-dijx.mp4?tag=27",
    "read_time": "2026-05-14T14:01:51",
    "is_uploaded": true,
    "upload_info": {
      "success": true,
      "message_id": 23765,
      "timestamp": "2026-05-14T14:01:55"
    },
    "is_downloaded": true,
    "download_info": {
      "success": true,
      "size": 475914,
      "size_mb": 0.45,
      "timestamp": "2026-05-14T14:01:53",
      "download_attempts": 0
    },
    "full_text": "вӣІпёҸрҹҢҠ https://t.co/XF2zzNy6mH",
    "publish_time": "2026-05-14T13:05:46"
  },
  {
    "file_name": "HIQU4mvbYAAShcB.jpg",
    "user": {
      "screen_name": "youan1144",
      "name": "YOUAN"
    },
    "media_type": "images",
    "url": "https://pbs.twimg.com/media/HIQU4mvbYAAShcB.jpg",
    "read_time": "2026-05-14T14:01:51",
    "is_uploaded": true,
    "upload_info": {
      "success": true,
      "message_id": 23766,
      "timestamp": "2026-05-14T14:01:56"
    },
    "is_downloaded": true,
    "download_info": {
      "success": true,
      "size": 239715,
      "size_mb": 0.23,
      "timestamp": "2026-05-14T14:01:55",
      "download_attempts": 0
    },
    "full_text": "й»‘иүІж¬ҫ https://t.co/diy8Ly7BsA",
    "publish_time": "2026-05-14T13:06:35"
  },
  {
    "file_name": "HIQU4msbEAAcKb-.jpg",
    "user": {
      "screen_name": "youan1144",
      "name": "YOUAN"
    },
    "media_type": "images",
    "url": "https://pbs.twimg.com/media/HIQU4msbEAAcKb-.jpg",
    "read_time": "2026-05-14T14:01:51",
    "is_uploaded": true,
    "upload_info": {
      "success": true,
      "message_id": 23767,
      "timestamp": "2026-05-14T14:01:57"
    },
    "is_downloaded": true,
    "download_info": {
      "success": true,
      "size": 197341,
      "size_mb": 0.19,
      "timestamp": "2026-05-14T14:01:56",
      "download_attempts": 0
    },
    "full_text": "й»‘иүІж¬ҫ https://t.co/diy8Ly7BsA",
    "publish_time": "2026-05-14T13:06:35"
  },
  {
    "file_name": "HIQU4h1bgAA14MW.jpg",
    "user": {
      "screen_name": "youan1144",
      "name": "YOUAN"
    },
    "media_type": "images",
    "url": "https://pbs.twimg.com/media/HIQU4h1bgAA14MW.jpg",
    "read_time": "2026-05-14T14:01:51",
    "is_uploaded": true,
    "upload_info": {
      "success": true,
      "message_id": 23768,
      "timestamp": "2026-05-14T14:01:58"
    },
    "is_downloaded": true,
    "download_info": {
      "success": true,
      "size": 210752,
      "size_mb": 0.2,
      "timestamp": "2026-05-14T14:01:58",
      "download_attempts": 0
    },
    "full_text": "й»‘иүІж¬ҫ https://t.co/diy8Ly7BsA",
    "publish_time": "2026-05-14T13:06:35"
  },
  {
    "file_name": "HIQU4mxbMAARPht.jpg",
    "user": {
      "screen_name": "youan1144",
      "name": "YOUAN"
    },
    "media_type": "images",
    "url": "https://pbs.twimg.com/media/HIQU4mxbMAARPht.jpg",
    "read_time": "2026-05-14T14:01:51",
    "is_uploaded": true,
    "upload_info": {
      "success": true,
      "message_id": 23769,
      "timestamp": "2026-05-14T14:02:00"
    },
    "is_downloaded": true,
    "download_info": {
      "success": true,
      "size": 234132,
      "size_mb": 0.22,
      "timestamp": "2026-05-14T14:01:59",
      "download_attempts": 0
    },
    "full_text": "й»‘иүІж¬ҫ https://t.co/diy8Ly7BsA",
    "publish_time": "2026-05-14T13:06:35"
  },
  {
    "file_name": "HIQVClNbQAAuK7w.jpg",
    "user": {
      "screen_name": "youan1144",
      "name": "YOUAN"
    },
    "media_type": "images",
    "url": "https://pbs.twimg.com/media/HIQVClNbQAAuK7w.jpg",
    "read_time": "2026-05-14T14:01:51",
    "is_uploaded": true,
    "upload_info": {
      "success": true,
      "message_id": 23770,
      "timestamp": "2026-05-14T14:02:01"
    },
    "is_downloaded": true,
    "download_info": {
      "success": true,
      "size": 212120,
      "size_mb": 0.2,
      "timestamp": "2026-05-14T14:02:00",
      "download_attempts": 0
    },
    "full_text": "й»‘иүІж¬ҫ https://t.co/fHggXRQMt0",
    "publish_time": "2026-05-14T13:07:11"
  },
  {
    "file_name": "HIQVClQaAAAo4Jn.jpg",
    "user": {
      "screen_name": "youan1144",
      "name": "YOUAN"
    },
    "media_type": "images",
    "url": "https://pbs.twimg.com/media/HIQVClQaAAAo4Jn.jpg",
    "read_time": "2026-05-14T14:01:51",
    "is_uploaded": true,
    "upload_info": {
      "success": true,
      "message_id": 23771,
      "timestamp": "2026-05-14T14:02:03"
    },
    "is_downloaded": true,
    "download_info": {
      "success": true,
      "size": 203864,
      "size_mb": 0.19,
      "timestamp": "2026-05-14T14:02:02",
      "download_attempts": 0
    },
    "full_text": "й»‘иүІж¬ҫ https://t.co/fHggXRQMt0",
    "publish_time": "2026-05-14T13:07:11"
  },
  {
    "file_name": "HIQVClVaIAA4DWR.jpg",
    "user": {
      "screen_name": "youan1144",
      "name": "YOUAN"
    },
    "media_type": "images",
    "url": "https://pbs.twimg.com/media/HIQVClVaIAA4DWR.jpg",
    "read_time": "2026-05-14T14:01:51",
    "is_uploaded": true,
    "upload_info": {
      "success": true,
      "message_id": 23772,
      "timestamp": "2026-05-14T14:02:04"
    },
    "is_downloaded": true,
    "download_info": {
      "success": true,
      "size": 165014,
      "size_mb": 0.16,
      "timestamp": "2026-05-14T14:02:03",
      "download_attempts": 0
    },
    "full_text": "й»‘иүІж¬ҫ https://t.co/fHggXRQMt0",
    "publish_time": "2026-05-14T13:07:11"
  },
  {
    "file_name": "HIQVClQa0AAIBhU.jpg",
    "user": {
      "screen_name": "youan1144",
      "name": "YOUAN"
    },
    "media_type": "images",
    "url": "https://pbs.twimg.com/media/HIQVClQa0AAIBhU.jpg",
    "read_time": "2026-05-14T14:01:51",
    "is_uploaded": true,
    "upload_info": {
      "success": true,
      "message_id": 23773,
      "timestamp": "2026-05-14T14:02:05"
    },
    "is_downloaded": true,
    "download_info": {
      "success": true,
      "size": 223151,
      "size_mb": 0.21,
      "timestamp": "2026-05-14T14:02:04",
      "download_attempts": 0
    },
    "full_text": "й»‘иүІж¬ҫ https://t.co/fHggXRQMt0",
    "publish_time": "2026-05-14T13:07:11"
  },
  {
    "file_name": "HIQVLSsboAAKafR.jpg",
    "user": {
      "screen_name": "youan1144",
      "name": "YOUAN"
    },
    "media_type": "images",
    "url": "https://pbs.twimg.com/media/HIQVLSsboAAKafR.jpg",
    "read_time": "2026-05-14T14:01:51",
    "is_uploaded": true,
    "upload_info": {
      "success": true,
      "message_id": 23774,
      "timestamp": "2026-05-14T14:02:07"
    },
    "is_downloaded": true,
    "download_info": {
      "success": true,
      "size": 193122,
      "size_mb": 0.18,
      "timestamp": "2026-05-14T14:02:06",
      "download_attempts": 0
    },
    "full_text": "зҷҪиүІж¬ҫ https://t.co/90UNVQCEDG",
    "publish_time": "2026-05-14T13:07:44"
  },
  {
    "file_name": "HIQVLSqbUAAz9jJ.jpg",
    "user": {
      "screen_name": "youan1144",
      "name": "YOUAN"
    },
    "media_type": "images",
    "url": "https://pbs.twimg.com/media/HIQVLSqbUAAz9jJ.jpg",
    "read_time": "2026-05-14T14:01:51",
    "is_uploaded": true,
    "upload_info": {
      "success": true,
      "message_id": 23775,
      "timestamp": "2026-05-14T14:02:08"
    },
    "is_downloaded": true,
    "download_info": {
      "success": true,
      "size": 222656,
      "size_mb": 0.21,
      "timestamp": "2026-05-14T14:02:07",
      "download_attempts": 0
    },
    "full_text": "зҷҪиүІж¬ҫ https://t.co/90UNVQCEDG",
    "publish_time": "2026-05-14T13:07:44"
  },
  {
    "file_name": "HIQVLStbUAAku85.jpg",
    "user": {
      "screen_name": "youan1144",
      "name": "YOUAN"
    },
    "media_type": "images",
    "url": "https://pbs.twimg.com/media/HIQVLStbUAAku85.jpg",
    "read_time": "2026-05-14T14:01:51",
    "is_uploaded": true,
    "upload_info": {
      "success": true,
      "message_id": 23776,
      "timestamp": "2026-05-14T14:02:09"
    },
    "is_downloaded": true,
    "download_info": {
      "success": true,
      "size": 208095,
      "size_mb": 0.2,
      "timestamp": "2026-05-14T14:02:08",
      "download_attempts": 0
    },
    "full_text": "зҷҪиүІж¬ҫ https://t.co/90UNVQCEDG",
    "publish_time": "2026-05-14T13:07:44"
  },
  {
    "file_name": "HIQVLSsbQAAQ7ja.jpg",
    "user": {
      "screen_name": "youan1144",
      "name": "YOUAN"
    },
    "media_type": "images",
    "url": "https://pbs.twimg.com/media/HIQVLSsbQAAQ7ja.jpg",
    "read_time": "2026-05-14T14:01:51",
    "is_uploaded": true,
    "upload_info": {
      "success": true,
      "message_id": 23777,
      "timestamp": "2026-05-14T14:02:11"
    },
    "is_downloaded": true,
    "download_info": {
      "success": true,
      "size": 241170,
      "size_mb": 0.23,
      "timestamp": "2026-05-14T14:02:10",
      "download_attempts": 0
    },
    "full_text": "зҷҪиүІж¬ҫ https://t.co/90UNVQCEDG",
    "publish_time": "2026-05-14T13:07:44"
  },
  {
    "file_name": "HIQZvVjbYAAz5Sh.jpg",
    "user": {
      "screen_name": "Mcsswest",
      "name": "жІЎжңүи„‘иўӢ"
    },
    "media_type": "images",
    "url": "https://pbs.twimg.com/media/HIQZvVjbYAAz5Sh.jpg",
    "read_time": "2026-05-14T14:01:51",
    "is_uploaded": true,
    "upload_info": {
      "success": true,
      "message_id": 23778,
      "timestamp": "2026-05-14T14:02:12"
    },
    "is_downloaded": true,
    "download_info": {
      "success": true,
      "size": 135488,
      "size_mb": 0.13,
      "timestamp": "2026-05-14T14:02:11",
      "download_attempts": 0
    },
    "full_text": "ж—©дёҠе…үзқҖеҮәеҺ»жӢҝеҶ°жЈҚпјҢйЎәжүӢеңЁеҺЁжҲҝжӢҚдәҶдёҖеј пјҢе“Ҳе“Ҳе“Ҳ https://t.co/XOoQUcGcHb",
    "publish_time": "2026-05-14T13:27:57"
  },
  {
    "file_name": "HIQZ3BmbMAEG6NA.jpg",
    "user": {
      "screen_name": "Mcsswest",
      "name": "жІЎжңүи„‘иўӢ"
    },
    "media_type": "images",
    "url": "https://pbs.twimg.com/media/HIQZ3BmbMAEG6NA.jpg",
    "read_time": "2026-05-14T14:01:51",
    "is_uploaded": true,
    "upload_info": {
      "success": true,
      "message_id": 23779,
      "timestamp": "2026-05-14T14:02:13"
    },
    "is_downloaded": true,
    "download_info": {
      "success": true,
      "size": 172362,
      "size_mb": 0.16,
      "timestamp": "2026-05-14T14:02:12",
      "download_attempts": 0
    },
    "full_text": "ж—©дёҠе…үзқҖеҮәеҺ»жӢҝеҶ°жЈҚпјҢйЎәжүӢеңЁеҺЁжҲҝжӢҚдәҶдёҖеј пјҢе“Ҳе“Ҳе“Ҳ https://t.co/XOoQUcGcHb",
    "publish_time": "2026-05-14T13:27:57"
  },
  {
    "file_name": "hoh2ZzoGgZPlUnrK.mp4",
    "user": {
      "screen_name": "77baxi",
      "name": "еҒҘиә«ж•ҷз»ғcdдјӘеЁҳ"
    },
    "media_type": "videos",
    "url": "https://video.twimg.com/amplify_video/2054566990006849536/vid/avc1/648x900/hoh2ZzoGgZPlUnrK.mp4?tag=27",
    "read_time": "2026-05-14T15:02:34",
    "is_uploaded": false,
    "upload_info": {
      "success": false,
      "error_type": "file_too_large",
      "message": "videosеӨ§е°Ҹи¶…ж Ү (103MB > 50MB)",
      "timestamp": "2026-05-14T15:02:36",
      "notification_sent": true
    },
    "is_downloaded": true,
    "download_info": {
      "success": true,
      "size": 108880451,
      "size_mb": 103.84,
      "timestamp": "2026-05-14T16:05:59",
      "download_attempts": 0
    },
    "full_text": "https://t.co/pBepKxSbWf",
    "publish_time": "2026-05-14T14:34:40"
  },
  {
    "file_name": "fwlDhppFUD0R6SFB.mp4",
    "user": {
      "screen_name": "youdi",
      "name": "HARUEHUN AIRRY зҺӢеӯҗйғЁиҗҪ"
    },
    "media_type": "videos",
    "url": "https://video.twimg.com/amplify_video/2054814908605517824/vid/avc1/1080x1920/fwlDhppFUD0R6SFB.mp4?tag=27",
    "read_time": "2026-05-14T15:02:34",
    "is_uploaded": true,
    "upload_info": {
      "success": true,
      "message_id": 23780,
      "timestamp": "2026-05-14T15:02:41"
    },
    "is_downloaded": true,
    "download_info": {
      "success": true,
      "size": 3392144,
      "size_mb": 3.24,
      "timestamp": "2026-05-14T15:02:38",
      "download_attempts": 0
    },
    "full_text": "https://t.co/7JzRarGtkm",
    "publish_time": "2026-05-14T14:54:57"
  },
  {
    "file_name": "HIQzLmRaoAAD23_.png",
    "user": {
      "screen_name": "youdi",
      "name": "HARUEHUN AIRRY зҺӢеӯҗйғЁиҗҪ"
    },
    "media_type": "images",
    "url": "https://pbs.twimg.com/media/HIQzLmRaoAAD23_.png",
    "read_time": "2026-05-14T16:05:56",
    "is_uploaded": true,
    "upload_info": {
      "success": true,
      "message_id": 23781,
      "timestamp": "2026-05-14T16:06:02"
    },
    "is_downloaded": true,
    "download_info": {
      "success": true,
      "size": 996028,
      "size_mb": 0.95,
      "timestamp": "2026-05-14T16:05:59",
      "download_attempts": 0
    },
    "full_text": "https://t.co/1NIRLOigoi",
    "publish_time": "2026-05-14T15:18:25"
  },
  {
    "file_name": "HIQzx7VbUAAD7N3.png",
    "user": {
      "screen_name": "youdi",
      "name": "HARUEHUN AIRRY зҺӢеӯҗйғЁиҗҪ"
    },
    "media_type": "images",
    "url": "https://pbs.twimg.com/media/HIQzx7VbUAAD7N3.png",
    "read_time": "2026-05-14T16:05:56",
    "is_uploaded": true,
    "upload_info": {
      "success": true,
      "message_id": 23782,
      "timestamp": "2026-05-14T16:06:04"
    },
    "is_downloaded": true,
    "download_info": {
      "success": true,
      "size": 664000,
      "size_mb": 0.63,
      "timestamp": "2026-05-14T16:06:02",
      "download_attempts": 0
    },
    "full_text": "https://t.co/v4Hi2iZX67",
    "publish_time": "2026-05-14T15:20:59"
  },
  {
    "file_name": "MyWYjidfCUqhLsTb.mp4",
    "user": {
      "screen_name": "youdi",
      "name": "HARUEHUN AIRRY зҺӢеӯҗйғЁиҗҪ"
    },
    "media_type": "videos",
    "url": "https://video.twimg.com/amplify_video/2054828695534362624/vid/avc1/1080x1920/MyWYjidfCUqhLsTb.mp4?tag=27",
    "read_time": "2026-05-14T16:05:56",
    "is_uploaded": true,
    "upload_info": {
      "success": true,
      "message_id": 23783,
      "timestamp": "2026-05-14T16:06:07"
    },
    "is_downloaded": true,
    "download_info": {
      "success": true,
      "size": 2729678,
      "size_mb": 2.6,
      "timestamp": "2026-05-14T16:06:04",
      "download_attempts": 0
    },
    "full_text": "https://t.co/mOd93hvSbI",
    "publish_time": "2026-05-14T15:39:04"
  },
  {
    "file_name": "HIRLK7qaoAA2M3P.jpg",
    "user": {
      "screen_name": "quebaner16598",
      "name": "quebaner"
    },
    "media_type": "images",
    "url": "https://pbs.twimg.com/media/HIRLK7qaoAA2M3P.jpg",
    "read_time": "2026-05-14T18:01:53",
    "is_uploaded": true,
    "upload_info": {
      "success": true,
      "message_id": 23784,
      "timestamp": "2026-05-14T18:01:56"
    },
    "is_downloaded": true,
    "download_info": {
      "success": true,
      "size": 91021,
      "size_mb": 0.09,
      "timestamp": "2026-05-14T18:01:54",
      "download_attempts": 0
    },
    "full_text": "рҹҗҲвҖҚв¬ӣ https://t.co/GlVx3G9sZR",
    "publish_time": "2026-05-14T17:03:27"
  },
  {
    "file_name": "HIRLK7jbsAAtKU_.jpg",
    "user": {
      "screen_name": "quebaner16598",
      "name": "quebaner"
    },
    "media_type": "images",
    "url": "https://pbs.twimg.com/media/HIRLK7jbsAAtKU_.jpg",
    "read_time": "2026-05-14T18:01:53",
    "is_uploaded": true,
    "upload_info": {
      "success": true,
      "message_id": 23785,
      "timestamp": "2026-05-14T18:01:57"
    },
    "is_downloaded": true,
    "download_info": {
      "success": true,
      "size": 86347,
      "size_mb": 0.08,
      "timestamp": "2026-05-14T18:01:56",
      "download_attempts": 0
    },
    "full_text": "рҹҗҲвҖҚв¬ӣ https://t.co/GlVx3G9sZR",
    "publish_time": "2026-05-14T17:03:27"
  },
  {
    "file_name": "HIROPheaQAAaZxD.jpg",
    "user": {
      "screen_name": "xiaofeilius",
      "name": "ж¬§е°ҸиұӘ"
    },
    "media_type": "images",
    "url": "https://pbs.twimg.com/media/HIROPheaQAAaZxD.jpg",
    "read_time": "2026-05-14T18:01:53",
    "is_uploaded": true,
    "upload_info": {
      "success": true,
      "message_id": 23786,
      "timestamp": "2026-05-14T18:01:59"
    },
    "is_downloaded": true,
    "download_info": {
      "success": true,
      "size": 131676,
      "size_mb": 0.13,
      "timestamp": "2026-05-14T18:01:57",
      "download_attempts": 0
    },
    "full_text": "рҹ§Ұрҹ©І е‘ізңҹи¶іпјҒ https://t.co/uyHRXpcsZY",
    "publish_time": "2026-05-14T17:16:35"
  },
  {
    "file_name": "HIROPhqaIAADG-K.jpg",
    "user": {
      "screen_name": "xiaofeilius",
      "name": "ж¬§е°ҸиұӘ"
    },
    "media_type": "images",
    "url": "https://pbs.twimg.com/media/HIROPhqaIAADG-K.jpg",
    "read_time": "2026-05-14T18:01:53",
    "is_uploaded": true,
    "upload_info": {
      "success": true,
      "message_id": 23787,
      "timestamp": "2026-05-14T18:02:00"
    },
    "is_downloaded": true,
    "download_info": {
      "success": true,
      "size": 128383,
      "size_mb": 0.12,
      "timestamp": "2026-05-14T18:01:59",
      "download_attempts": 0
    },
    "full_text": "рҹ§Ұрҹ©І е‘ізңҹи¶іпјҒ https://t.co/uyHRXpcsZY",
    "publish_time": "2026-05-14T17:16:35"
  },
  {
    "file_name": "HIROPhpbsAA3yO4.jpg",
    "user": {
      "screen_name": "xiaofeilius",
      "name": "ж¬§е°ҸиұӘ"
    },
    "media_type": "images",
    "url": "https://pbs.twimg.com/media/HIROPhpbsAA3yO4.jpg",
    "read_time": "2026-05-14T18:01:53",
    "is_uploaded": true,
    "upload_info": {
      "success": true,
      "message_id": 23788,
      "timestamp": "2026-05-14T18:02:02"
    },
    "is_downloaded": true,
    "download_info": {
      "success": true,
      "size": 113838,
      "size_mb": 0.11,
      "timestamp": "2026-05-14T18:02:00",
      "download_attempts": 0
    },
    "full_text": "рҹ§Ұрҹ©І е‘ізңҹи¶іпјҒ https://t.co/uyHRXpcsZY",
    "publish_time": "2026-05-14T17:16:35"
  },
  {
    "file_name": "HIROPhgbsAAv2kc.jpg",
    "user": {
      "screen_name": "xiaofeilius",
      "name": "ж¬§е°ҸиұӘ"
    },
    "media_type": "images",
    "url": "https://pbs.twimg.com/media/HIROPhgbsAAv2kc.jpg",
    "read_time": "2026-05-14T18:01:53",
    "is_uploaded": true,
    "upload_info": {
      "success": true,
      "message_id": 23789,
      "timestamp": "2026-05-14T18:02:03"
    },
    "is_downloaded": true,
    "download_info": {
      "success": true,
      "size": 179910,
      "size_mb": 0.17,
      "timestamp": "2026-05-14T18:02:02",
      "download_attempts": 0
    },
    "full_text": "рҹ§Ұрҹ©І е‘ізңҹи¶іпјҒ https://t.co/uyHRXpcsZY",
    "publish_time": "2026-05-14T17:16:35"
  },
  {
    "file_name": "HIRTq2WbMAA85N8.jpg",
    "user": {
      "screen_name": "isheepgoes",
      "name": "дёҖиЎҢ"
    },
    "media_type": "images",
    "url": "https://pbs.twimg.com/media/HIRTq2WbMAA85N8.jpg",
    "read_time": "2026-05-14T18:01:53",
    "is_uploaded": true,
    "upload_info": {
      "success": true,
      "message_id": 23790,
      "timestamp": "2026-05-14T18:02:04"
    },
    "is_downloaded": true,
    "download_info": {
      "success": true,
      "size": 162111,
      "size_mb": 0.15,
      "timestamp": "2026-05-14T18:02:03",
      "download_attempts": 0
    },
    "full_text": "https://t.co/n7nHMrxili",
    "publish_time": "2026-05-14T17:40:21"
  },
  {
    "file_name": "HIRTq3dacAA6Wgx.jpg",
    "user": {
      "screen_name": "isheepgoes",
      "name": "дёҖиЎҢ"
    },
    "media_type": "images",
    "url": "https://pbs.twimg.com/media/HIRTq3dacAA6Wgx.jpg",
    "read_time": "2026-05-14T18:01:53",
    "is_uploaded": true,
    "upload_info": {
      "success": true,
      "message_id": 23791,
      "timestamp": "2026-05-14T18:02:05"
    },
    "is_downloaded": true,
    "download_info": {
      "success": true,
      "size": 263300,
      "size_mb": 0.25,
      "timestamp": "2026-05-14T18:02:04",
      "download_attempts": 0
    },
    "full_text": "https://t.co/n7nHMrxili",
    "publish_time": "2026-05-14T17:40:21"
  },
  {
    "file_name": "HIRTrPiaEAA3C8Q.jpg",
    "user": {
      "screen_name": "isheepgoes",
      "name": "дёҖиЎҢ"
    },
    "media_type": "images",
    "url": "https://pbs.twimg.com/media/HIRTrPiaEAA3C8Q.jpg",
    "read_time": "2026-05-14T18:01:53",
    "is_uploaded": true,
    "upload_info": {
      "success": true,
      "message_id": 23792,
      "timestamp": "2026-05-14T18:02:06"
    },
    "is_downloaded": true,
    "download_info": {
      "success": true,
      "size": 359349,
      "size_mb": 0.34,
      "timestamp": "2026-05-14T18:02:05",
      "download_attempts": 0
    },
    "full_text": "https://t.co/n7nHMrxili",
    "publish_time": "2026-05-14T17:40:21"
  }
]