[
  {
    "file_name": "RIOe_BGMJ1_mNmVz.mp4",
    "user": {
      "screen_name": "QQONEdad",
      "name": "QQONE"
    },
    "media_type": "videos",
    "url": "https://video.twimg.com/amplify_video/2042961521312174082/vid/avc1/1080x1798/RIOe_BGMJ1_mNmVz.mp4?tag=21",
    "read_time": "2026-04-12T01:01:25",
    "is_uploaded": false,
    "upload_info": {
      "success": false,
      "error_type": "file_too_large",
      "message": "videos大小超标 (346MB > 50MB)",
      "timestamp": "2026-04-12T01:01:29",
      "notification_sent": false
    },
    "is_downloaded": false,
    "download_info": {
      "success": true,
      "size": 363267367,
      "size_mb": 346.44,
      "timestamp": "2026-04-12T01:01:29",
      "download_attempts": 0
    },
    "full_text": "https://t.co/uJhhLHgeQe",
    "publish_time": "2026-04-12T00:37:34"
  }
]