[
  {
    "user": {
      "screenName": "MaryBak64398222",
      "name": "直男调教s"
    },
    "images": [],
    "videos": [
      "https://video.twimg.com/ext_tw_video/2043359152509177856/pu/vid/avc1/720x952/GivizORctt2u_g7V.mp4?tag=12"
    ],
    "expandUrls": [],
    "tweetUrl": "https://x.com/MaryBak64398222/status/2043359200815042871",
    "fullText": "这两天刷到几个宝藏推主，交流的也挺好的，结果今天上来看号都没了… \n也不知道是X官方搞的，还是告密🐔们又开始犯剑咯~  踏踏实实的欣赏作品不好么，一个个的那么喜欢举报🥴 心累 https://t.co/Vz1KQGXkWF",
    "publishTime": "2026-04-13T00:02:51"
  },
  {
    "user": {
      "screenName": "Chris_SDD",
      "name": "Chris"
    },
    "images": [],
    "videos": [
      "https://video.twimg.com/tweet_video/HFt0TiIXwAAUagW.mp4"
    ],
    "expandUrls": [],
    "tweetUrl": "https://x.com/Chris_SDD/status/2043359292267385043",
    "fullText": "💕💦 https://t.co/FnEO0AS7Xv",
    "publishTime": "2026-04-13T00:03:13"
  },
  {
    "user": {
      "screenName": "huohuo0707330",
      "name": "嚯"
    },
    "images": [
      "https://pbs.twimg.com/media/HFt9rTDaIAE8Gce.jpg"
    ],
    "videos": [],
    "expandUrls": [],
    "tweetUrl": "https://x.com/huohuo0707330/status/2043365044629725398",
    "fullText": "来认真学习 #上海 https://t.co/HZMTdIkpYJ",
    "publishTime": "2026-04-13T00:26:05"
  },
  {
    "user": {
      "screenName": "chuanzhang0320",
      "name": "Appetency."
    },
    "images": [],
    "videos": [],
    "expandUrls": [],
    "tweetUrl": "https://x.com/chuanzhang0320/status/2043392312798282094",
    "fullText": "14号到 #南宁",
    "publishTime": "2026-04-13T02:14:26"
  },
  {
    "user": {
      "screenName": "hopechen0312",
      "name": "hope"
    },
    "images": [],
    "videos": [
      "https://video.twimg.com/amplify_video/2043398360611328000/vid/avc1/1280x720/6pMCGD1_Ik889gk4.mp4?tag=21"
    ],
    "expandUrls": [],
    "tweetUrl": "https://x.com/hopechen0312/status/2043398477242343738",
    "fullText": "好吃的 @sluttylouisxxx \n\n不管吃幾次還是很美味\n\n這次就讓他自己射囉 https://t.co/yTpJ9bi6eR",
    "publishTime": "2026-04-13T02:38:56"
  },
  {
    "user": {
      "screenName": "kueerkueer",
      "name": "kueer"
    },
    "images": [],
    "videos": [
      "https://video.twimg.com/amplify_video/1983556488405585920/vid/avc1/1080x1920/rkYbjVbsrcxOLgE_.mp4?tag=21"
    ],
    "expandUrls": [],
    "tweetUrl": "https://x.com/kueerkueer/status/2043401120996057299",
    "fullText": "https://t.co/dvngC3buZq",
    "publishTime": "2026-04-13T02:49:26"
  },
  {
    "user": {
      "screenName": "kueerkueer",
      "name": "kueer"
    },
    "images": [],
    "videos": [
      "https://video.twimg.com/ext_tw_video/2043103704090316800/pu/vid/avc1/480x480/-l_IFCIWYdryL1z0.mp4?tag=12"
    ],
    "expandUrls": [],
    "tweetUrl": "https://x.com/kueerkueer/status/2043408082504720775",
    "fullText": "https://t.co/XSw6lhYuwu",
    "publishTime": "2026-04-13T03:17:06"
  },
  {
    "user": {
      "screenName": "Forestwoodwood",
      "name": "FOREST ALBUM 🏳️‍🌈"
    },
    "images": [],
    "videos": [
      "https://video.twimg.com/amplify_video/2043418719603580928/vid/avc1/1242x2214/DQFuKghnBJ-kcJA1.mp4?tag=21"
    ],
    "expandUrls": [],
    "tweetUrl": "https://x.com/Forestwoodwood/status/2043419538818281837",
    "fullText": ".\nContinuing 🌈曼谷「泼水节」Asia's Biggest Gay Dance Festival GCIRCUIT  IG：gcircuit 20thAnniversary  \n#SongKran2026 \nThank You for the video 👉dong_nateephat @DNateephat \nIG：dong_nateephat https://t.co/WJVi7ClEnZ",
    "publishTime": "2026-04-13T04:02:37"
  },
  {
    "user": {
      "screenName": "eric_kk97",
      "name": "ManFeed🍆"
    },
    "images": [
      "https://pbs.twimg.com/media/HFu1P9RbcAAR6vo.jpg",
      "https://pbs.twimg.com/media/HFu1P9LagAAL9gV.jpg"
    ],
    "videos": [],
    "expandUrls": [],
    "tweetUrl": "https://x.com/eric_kk97/status/2043426147053228414",
    "fullText": "https://t.co/qcaEYSQt7h",
    "publishTime": "2026-04-13T04:28:53"
  },
  {
    "user": {
      "screenName": "Forestwoodwood",
      "name": "FOREST ALBUM 🏳️‍🌈"
    },
    "images": [
      "https://pbs.twimg.com/media/HFu2r_NbMAAo6Jn.jpg",
      "https://pbs.twimg.com/media/HFu2r_Oa4AAgkSv.jpg",
      "https://pbs.twimg.com/media/HFu2r_Ma0AAtmQM.jpg",
      "https://pbs.twimg.com/media/HFu2r_MbIAAr75B.jpg"
    ],
    "videos": [],
    "expandUrls": [],
    "tweetUrl": "https://x.com/Forestwoodwood/status/2043427727370494377",
    "fullText": "·\nXXX模特：廉書宇💪🏾 （002）在摄影大师任壬的Ebook👉 HORMONE 26 -牡丹亭｜我没有资源是在网上看到下载的｜模特有抖音号和red notes👉他的昵称是“一米九的大魔王”，首页写著：职业健身运功员，素质不高，性別男爱女性…… https://t.co/zRa6rgUq4r",
    "publishTime": "2026-04-13T04:35:09"
  },
  {
    "user": {
      "screenName": "Forestwoodwood",
      "name": "FOREST ALBUM 🏳️‍🌈"
    },
    "images": [
      "https://pbs.twimg.com/media/HFu3nwpawAAfu3R.jpg",
      "https://pbs.twimg.com/media/HFu3nwzb0AAv1d0.jpg",
      "https://pbs.twimg.com/media/HFu3nwubAAA30El.jpg",
      "https://pbs.twimg.com/media/HFu3nwvaEAAFatm.jpg"
    ],
    "videos": [],
    "expandUrls": [],
    "tweetUrl": "https://x.com/Forestwoodwood/status/2043428754916262176",
    "fullText": "·\nXXX模特：廉書宇💪🏾 （001）在摄影大师任壬的Ebook👉 HORMONE 26 -牡丹亭｜我没有资源是在网上看到下载的｜模特有抖音号和red notes👉他的昵称是“一米九的大魔王”，首页写著：职业健身运功员，素质不高，性別男爱女性…… https://t.co/scqFYzVtEm",
    "publishTime": "2026-04-13T04:39:14"
  },
  {
    "user": {
      "screenName": "eric_kk97",
      "name": "ManFeed🍆"
    },
    "images": [
      "https://pbs.twimg.com/media/HFu36FnbEAAbmGZ.jpg"
    ],
    "videos": [],
    "expandUrls": [],
    "tweetUrl": "https://x.com/eric_kk97/status/2043429068478333001",
    "fullText": "nailangyu https://t.co/9mR7NZr7Rt",
    "publishTime": "2026-04-13T04:40:29"
  },
  {
    "user": {
      "screenName": "toplcjfjv",
      "name": "發發top"
    },
    "images": [],
    "videos": [
      "https://video.twimg.com/amplify_video/2043429901433442304/vid/avc1/720x1280/XA69wKog5rSxujjL.mp4?tag=21"
    ],
    "expandUrls": [],
    "tweetUrl": "https://x.com/toplcjfjv/status/2043430045700808951",
    "fullText": "懶覺真是神奇的器官，明明感冒變嚴重，還是可以睡到一半硬醒… https://t.co/j7z8ipholS",
    "publishTime": "2026-04-13T04:44:22"
  },
  {
    "user": {
      "screenName": "toplcjfjv",
      "name": "發發top"
    },
    "images": [],
    "videos": [
      "https://video.twimg.com/amplify_video/2043431159196184576/vid/avc1/720x1280/FQJIJtkZxsmtpDmc.mp4?tag=21"
    ],
    "expandUrls": [],
    "tweetUrl": "https://x.com/toplcjfjv/status/2043431306177167719",
    "fullText": "不要問我今年為什麼沒去潑水節😷 https://t.co/UkUZRsEZtR",
    "publishTime": "2026-04-13T04:49:23"
  },
  {
    "user": {
      "screenName": "Forestwoodwood",
      "name": "FOREST ALBUM 🏳️‍🌈"
    },
    "images": [],
    "videos": [
      "https://video.twimg.com/amplify_video/2043438923033219072/vid/avc1/1242x2214/WLfjyzHtI3TevLdp.mp4?tag=21"
    ],
    "expandUrls": [],
    "tweetUrl": "https://x.com/Forestwoodwood/status/2043439774607049024",
    "fullText": ".\n花絮/behind event 🌈曼谷「泼水节」Asia's Biggest Gay Dance Festival GCIRCUIT  IG：gcircuit 20thAnniversary  \n#SongKran2026 \nThank You for the video 👉dong_nateephat @DNateephat \nIG：dong_nateephat https://t.co/vIMEvhA26O",
    "publishTime": "2026-04-13T05:23:02"
  },
  {
    "user": {
      "screenName": "Rex1719124799",
      "name": "Rex大鹏"
    },
    "images": [
      "https://pbs.twimg.com/media/HFvB2HiawAA_Gne.jpg"
    ],
    "videos": [],
    "expandUrls": [],
    "tweetUrl": "https://x.com/Rex1719124799/status/2043439997345583492",
    "fullText": "跪好，别动。我的手会告诉你，什么叫真正的惩罚。你越挣扎，我越不会停。 https://t.co/G1qMB1kR36",
    "publishTime": "2026-04-13T05:23:55"
  },
  {
    "user": {
      "screenName": "Forestwoodwood",
      "name": "FOREST ALBUM 🏳️‍🌈"
    },
    "images": [
      "https://pbs.twimg.com/media/HFvGygra8AA9vck.jpg",
      "https://pbs.twimg.com/media/HFvGygqbkAAAaAR.jpg",
      "https://pbs.twimg.com/media/HFvGygoaoAA8Tvp.jpg",
      "https://pbs.twimg.com/media/HFvGygpaMAAAfZm.jpg"
    ],
    "videos": [],
    "expandUrls": [],
    "tweetUrl": "https://x.com/Forestwoodwood/status/2043445431787720729",
    "fullText": "·\n&lt; 健身模特·系列&gt;\n\n摄影师 肖一遣 @xiao1qian \n\n健身模特/教练👉北体小何🥇\n\n📍上海 \n. https://t.co/LFBQBC5zWA",
    "publishTime": "2026-04-13T05:45:30"
  },
  {
    "user": {
      "screenName": "Forestwoodwood",
      "name": "FOREST ALBUM 🏳️‍🌈"
    },
    "images": [
      "https://pbs.twimg.com/media/HFvHMFUbcAAdKCV.jpg",
      "https://pbs.twimg.com/media/HFvHMFgbsAA5c1z.jpg",
      "https://pbs.twimg.com/media/HFvHMFSacAAn6kB.jpg",
      "https://pbs.twimg.com/media/HFvHMFdacAAZ_W-.jpg"
    ],
    "videos": [],
    "expandUrls": [],
    "tweetUrl": "https://x.com/Forestwoodwood/status/2043445870230909136",
    "fullText": "https://t.co/OyMPJGc2cR",
    "publishTime": "2026-04-13T05:47:15"
  },
  {
    "user": {
      "screenName": "eric_kk97",
      "name": "ManFeed🍆"
    },
    "images": [
      "https://pbs.twimg.com/media/HFvHTtQbEAA5SMZ.jpg"
    ],
    "videos": [],
    "expandUrls": [],
    "tweetUrl": "https://x.com/eric_kk97/status/2043446001961410964",
    "fullText": "ducnguyen_fitness https://t.co/XbARe4z4zR",
    "publishTime": "2026-04-13T05:47:46"
  },
  {
    "user": {
      "screenName": "eric_kk97",
      "name": "ManFeed🍆"
    },
    "images": [
      "https://pbs.twimg.com/media/HFvHcp0aAAA3G2M.jpg",
      "https://pbs.twimg.com/media/HFvHcplbUAA43sT.jpg"
    ],
    "videos": [],
    "expandUrls": [],
    "tweetUrl": "https://x.com/eric_kk97/status/2043446156383150423",
    "fullText": "sebbyoppar https://t.co/3qxbdH5cbK",
    "publishTime": "2026-04-13T05:48:23"
  },
  {
    "user": {
      "screenName": "chuanzhang0320",
      "name": "Appetency."
    },
    "images": [],
    "videos": [
      "https://video.twimg.com/amplify_video/2043448227698282496/vid/avc1/1280x720/0vo_dSyaLZhGS_E5.mp4?tag=21"
    ],
    "expandUrls": [],
    "tweetUrl": "https://x.com/chuanzhang0320/status/2043448298841989588",
    "fullText": "对了对了，还有这个视角 https://t.co/MD6uJUbxJJ",
    "publishTime": "2026-04-13T05:56:54"
  },
  {
    "user": {
      "screenName": "Forestwoodwood",
      "name": "FOREST ALBUM 🏳️‍🌈"
    },
    "images": [],
    "videos": [],
    "expandUrls": [],
    "tweetUrl": "https://x.com/Forestwoodwood/status/2043469032222015568",
    "fullText": "🌈祝贺他们20周年之际快乐🎊",
    "publishTime": "2026-04-13T07:19:17"
  },
  {
    "user": {
      "screenName": "growncz",
      "name": "阿巴阿巴"
    },
    "images": [
      "https://pbs.twimg.com/media/HFvl4xvb0AAV5s9.jpg",
      "https://pbs.twimg.com/media/HFvl4xubsAA59WD.jpg",
      "https://pbs.twimg.com/media/HFvl4xxakAAVoNt.jpg"
    ],
    "videos": [
      "https://video.twimg.com/amplify_video/2043479619580649472/vid/avc1/720x1280/Vyxyq9-IYqMEHSkU.mp4?tag=21"
    ],
    "expandUrls": [],
    "tweetUrl": "https://x.com/growncz/status/2043479682826539513",
    "fullText": "嘻嘻☺️过了一个愉快的周末～ https://t.co/6MvMvlNDoh",
    "publishTime": "2026-04-13T08:01:37"
  },
  {
    "user": {
      "screenName": "eric_kk97",
      "name": "ManFeed🍆"
    },
    "images": [
      "https://pbs.twimg.com/media/HFvn3ITbAAAr9HS.jpg"
    ],
    "videos": [],
    "expandUrls": [],
    "tweetUrl": "https://x.com/eric_kk97/status/2043481796101501185",
    "fullText": "juzconam https://t.co/adsucV8NP3",
    "publishTime": "2026-04-13T08:10:00"
  },
  {
    "user": {
      "screenName": "chounizadi2021",
      "name": "男神传送门"
    },
    "images": [
      "https://pbs.twimg.com/media/HFv64H8XIAAAe94.jpg",
      "https://pbs.twimg.com/media/HFv64H8WcAA8kRX.jpg"
    ],
    "videos": [],
    "expandUrls": [],
    "tweetUrl": "https://x.com/chounizadi2021/status/2043502709832040797",
    "fullText": "【粉丝投稿】谁知道这个是谁，知道的请私信。第一个私信开门的可以免费寻人。（发帖寻人收费🧧，vpn不稳定，寻人/征友/买男性用品加个人VX（SYLjiankang2023），注明来意否则不通过） https://t.co/hrttp4OeSP",
    "publishTime": "2026-04-13T09:33:07"
  },
  {
    "user": {
      "screenName": "chounizadi2021",
      "name": "男神传送门"
    },
    "images": [
      "https://pbs.twimg.com/media/HFv7Q9nWQAAcBIn.jpg",
      "https://pbs.twimg.com/media/HFv7Q7AW8AEJGIX.jpg",
      "https://pbs.twimg.com/media/HFv7Q7DXoAARNv-.jpg"
    ],
    "videos": [],
    "expandUrls": [],
    "tweetUrl": "https://x.com/chounizadi2021/status/2043503141295964461",
    "fullText": "【粉丝投稿】谁知道这个抖音博主的推特ID，知道的请私信。第一个私信开门的可以免费寻人。（发帖寻人收费🧧，vpn不稳定，寻人/征友/买男性用品加个人VX（SYLjiankang2023），注明来意否则不通过） https://t.co/J38372D6yS",
    "publishTime": "2026-04-13T09:34:49"
  },
  {
    "user": {
      "screenName": "eric_kk97",
      "name": "ManFeed🍆"
    },
    "images": [
      "https://pbs.twimg.com/media/HFwC7NDaEAA7p4F.jpg"
    ],
    "videos": [],
    "expandUrls": [],
    "tweetUrl": "https://x.com/eric_kk97/status/2043511552192749801",
    "fullText": "wolf_x1x https://t.co/m03A9Qx2Ac",
    "publishTime": "2026-04-13T10:08:15"
  },
  {
    "user": {
      "screenName": "wwxia8898",
      "name": "罗夏 （上海）"
    },
    "images": [
      "https://pbs.twimg.com/media/HFwEUDAbsAAfh3M.jpg"
    ],
    "videos": [],
    "expandUrls": [],
    "tweetUrl": "https://x.com/wwxia8898/status/2043513086397841571",
    "fullText": "深圳 https://t.co/s0tPuY4BHl",
    "publishTime": "2026-04-13T10:14:21"
  },
  {
    "user": {
      "screenName": "BBoy1069",
      "name": "我是臭直男"
    },
    "images": [],
    "videos": [
      "https://video.twimg.com/amplify_video/2043521782297309184/vid/avc1/720x1280/br-_mfcdUFNhPvk1.mp4?tag=14"
    ],
    "expandUrls": [],
    "tweetUrl": "https://x.com/BBoy1069/status/2043521818548637757",
    "fullText": "【2026年4月13日】今日資源已經更新！以下視頻與更新資源無關！ https://t.co/2JjE5wpBQT",
    "publishTime": "2026-04-13T10:49:02"
  },
  {
    "user": {
      "screenName": "kaka_lac",
      "name": "kaka"
    },
    "images": [],
    "videos": [
      "https://video.twimg.com/amplify_video/2043534898523422721/vid/avc1/720x1280/W7_l-3K_UzgO8KQi.mp4?tag=21"
    ],
    "expandUrls": [
      "http://t.me/cc9699"
    ],
    "tweetUrl": "https://x.com/kaka_lac/status/2043534976940179751",
    "fullText": "为了回馈广大粉丝对我的支持！今天进我福利群🌹的将不收取任何费用，24h免费对我的粉丝们限时无门槛📷进入，可观看所有视频和写真噢！ 资源管够 手慢拍大腿\n \n唯一通道: https://t.co/tPzd8HPhqj\n暗号:  Ak https://t.co/MQbHpRem7U",
    "publishTime": "2026-04-13T11:41:20"
  },
  {
    "user": {
      "screenName": "youdi",
      "name": "HARUEHUN AIRRY 王子部落"
    },
    "images": [
      "https://pbs.twimg.com/media/HFwfZZSbgAEcKub.jpg"
    ],
    "videos": [],
    "expandUrls": [],
    "tweetUrl": "https://x.com/youdi/status/2043542858779779317",
    "fullText": "https://t.co/M6ViSvDswG",
    "publishTime": "2026-04-13T12:12:39"
  },
  {
    "user": {
      "screenName": "YoungOu123",
      "name": "Young Ou"
    },
    "images": [],
    "videos": [
      "https://video.twimg.com/amplify_video/2043543650890878976/vid/avc1/720x1280/XMqJ38IW5f_gi76U.mp4?tag=21"
    ],
    "expandUrls": [],
    "tweetUrl": "https://x.com/YoungOu123/status/2043543711448174789",
    "fullText": "周1️⃣坏 https://t.co/LHRLtxXDEs",
    "publishTime": "2026-04-13T12:16:02"
  },
  {
    "user": {
      "screenName": "Forestwoodwood",
      "name": "FOREST ALBUM 🏳️‍🌈"
    },
    "images": [],
    "videos": [
      "https://video.twimg.com/amplify_video/2043557858437222400/vid/avc1/1240x1650/OMAGB_93Jj0W3sqc.mp4?tag=21"
    ],
    "expandUrls": [],
    "tweetUrl": "https://x.com/Forestwoodwood/status/2043557948912509154",
    "fullText": "•\nSongkran 「泼水节」。它是泰国及中国云南傣族等地区的传统新年，时间通常在每年的公历4月13日至15日左右。 该节日通常持续三天,隆重、最热闹的传统节日。\n视频：帅哥｛ 草莓香蕉车厘子｝-王小强-  三天在曼谷泼水💦。。。 https://t.co/BmKLEjHpsE",
    "publishTime": "2026-04-13T13:12:37"
  },
  {
    "user": {
      "screenName": "hhh752093296",
      "name": "大力宝宝"
    },
    "images": [],
    "videos": [
      "https://video.twimg.com/amplify_video/2043564676689330176/vid/avc1/640x320/MvVCemCDe8VFEmWx.mp4?tag=21"
    ],
    "expandUrls": [
      "http://t.me/TT9622"
    ],
    "tweetUrl": "https://x.com/hhh752093296/status/2043564791290286479",
    "fullText": "粉丝要求限时福利今天0\n联系TG： https://t.co/SHAUtA2pwD\n进来即可观看我所有完整版视频，私人未发布写真，仅限粉丝来\n    暗号：001 https://t.co/7Y8vhhTEdW",
    "publishTime": "2026-04-13T13:39:48"
  },
  {
    "user": {
      "screenName": "chounizadi2021",
      "name": "男神传送门"
    },
    "images": [],
    "videos": [],
    "expandUrls": [],
    "tweetUrl": "https://x.com/chounizadi2021/status/2043565297701990559",
    "fullText": "太平年太好看了",
    "publishTime": "2026-04-13T13:41:49"
  },
  {
    "user": {
      "screenName": "KevinLeeYoung92",
      "name": "KevinLeeYoung"
    },
    "images": [],
    "videos": [],
    "expandUrls": [],
    "tweetUrl": "https://x.com/KevinLeeYoung92/status/2043568665690562805",
    "fullText": "❤️",
    "publishTime": "2026-04-13T13:55:12"
  },
  {
    "user": {
      "screenName": "youdi",
      "name": "HARUEHUN AIRRY 王子部落"
    },
    "images": [
      "https://pbs.twimg.com/media/HFxFaowbwAAvITi.jpg",
      "https://pbs.twimg.com/media/HFxFaorbUAAoKZ5.jpg"
    ],
    "videos": [],
    "expandUrls": [],
    "tweetUrl": "https://x.com/youdi/status/2043584663395209612",
    "fullText": "https://t.co/ehSh2TFdlD",
    "publishTime": "2026-04-13T14:58:46"
  },
  {
    "user": {
      "screenName": "youdi",
      "name": "HARUEHUN AIRRY 王子部落"
    },
    "images": [],
    "videos": [
      "https://video.twimg.com/amplify_video/2043588798953725952/vid/avc1/720x1280/f-elzcb0eTm0SSMT.mp4?tag=21"
    ],
    "expandUrls": [],
    "tweetUrl": "https://x.com/youdi/status/2043588875122332030",
    "fullText": "https://t.co/PvaKCFaSN7",
    "publishTime": "2026-04-13T15:15:30"
  },
  {
    "user": {
      "screenName": "youdi",
      "name": "HARUEHUN AIRRY 王子部落"
    },
    "images": [
      "https://pbs.twimg.com/media/HFxJlAHbUAAlVq8.jpg"
    ],
    "videos": [],
    "expandUrls": [],
    "tweetUrl": "https://x.com/youdi/status/2043589237745000565",
    "fullText": "https://t.co/bwCmTnhylP",
    "publishTime": "2026-04-13T15:16:56"
  },
  {
    "user": {
      "screenName": "youdi",
      "name": "HARUEHUN AIRRY 王子部落"
    },
    "images": [
      "https://pbs.twimg.com/media/HFxJm6KbIAAdut0.jpg"
    ],
    "videos": [],
    "expandUrls": [],
    "tweetUrl": "https://x.com/youdi/status/2043589270246699519",
    "fullText": "https://t.co/5DwEaOLa5O",
    "publishTime": "2026-04-13T15:17:04"
  },
  {
    "user": {
      "screenName": "eric_kk97",
      "name": "ManFeed🍆"
    },
    "images": [
      "https://pbs.twimg.com/media/HFxZstzacAAzHLh.jpg"
    ],
    "videos": [],
    "expandUrls": [],
    "tweetUrl": "https://x.com/eric_kk97/status/2043606961833509230",
    "fullText": "sasuke_monkey https://t.co/6KfnUlMZYT",
    "publishTime": "2026-04-13T16:27:22"
  },
  {
    "user": {
      "screenName": "r1929979006488",
      "name": "ia__"
    },
    "images": [],
    "videos": [
      "https://video.twimg.com/amplify_video/2043609899029127168/vid/avc1/720x1280/9hLSAPs5OsndvfMj.mp4?tag=21"
    ],
    "expandUrls": [],
    "tweetUrl": "https://x.com/r1929979006488/status/2043609963587936523",
    "fullText": "https://t.co/J7YiuDwmS1",
    "publishTime": "2026-04-13T16:39:18"
  },
  {
    "user": {
      "screenName": "junglewildwild",
      "name": "丛林野兽"
    },
    "images": [
      "https://pbs.twimg.com/media/HFxd0a_bMAAhPai.jpg",
      "https://pbs.twimg.com/media/HFxd0a-b0AA41SI.jpg",
      "https://pbs.twimg.com/media/HFxd0a9a8AA0Shs.jpg",
      "https://pbs.twimg.com/media/HFxd0a9bkAA9whA.jpg"
    ],
    "videos": [],
    "expandUrls": [],
    "tweetUrl": "https://x.com/junglewildwild/status/2043611495125467318",
    "fullText": "https://t.co/E6LhHkyNK3",
    "publishTime": "2026-04-13T16:45:23"
  },
  {
    "user": {
      "screenName": "eric_kk97",
      "name": "ManFeed🍆"
    },
    "images": [
      "https://pbs.twimg.com/media/HFxg7qYa4AAW1t7.jpg"
    ],
    "videos": [],
    "expandUrls": [],
    "tweetUrl": "https://x.com/eric_kk97/status/2043614912975651253",
    "fullText": "https://t.co/wHgOVXMlsk",
    "publishTime": "2026-04-13T16:58:58"
  },
  {
    "user": {
      "screenName": "RuiHengJin",
      "name": "H."
    },
    "images": [],
    "videos": [
      "https://video.twimg.com/amplify_video/2043616392763854848/vid/avc1/720x960/Np_vIwPVVaCT8UYO.mp4?tag=21"
    ],
    "expandUrls": [],
    "tweetUrl": "https://x.com/RuiHengJin/status/2043616458916376590",
    "fullText": "🫵 https://t.co/JQ3SiQcJNF",
    "publishTime": "2026-04-13T17:05:07"
  },
  {
    "user": {
      "screenName": "huohuo0707330",
      "name": "嚯"
    },
    "images": [
      "https://pbs.twimg.com/media/HFxv3Web0AAaoGk.jpg"
    ],
    "videos": [],
    "expandUrls": [],
    "tweetUrl": "https://x.com/huohuo0707330/status/2043631338046275657",
    "fullText": "课有点水  训练不能水 #上海 https://t.co/5xjJvqBWgG",
    "publishTime": "2026-04-13T18:04:14"
  },
  {
    "user": {
      "screenName": "Forestwoodwood",
      "name": "FOREST ALBUM 🏳️‍🌈"
    },
    "images": [],
    "videos": [],
    "expandUrls": [],
    "tweetUrl": "https://x.com/Forestwoodwood/status/2043632924822773924",
    "fullText": "·\n小徐有新的采访了……专题👉我和Sman ，我明天发出！",
    "publishTime": "2026-04-13T18:10:32"
  },
  {
    "user": {
      "screenName": "eric_kk97",
      "name": "ManFeed🍆"
    },
    "images": [
      "https://pbs.twimg.com/media/HFx7xtUbAAA8GJG.jpg"
    ],
    "videos": [],
    "expandUrls": [],
    "tweetUrl": "https://x.com/eric_kk97/status/2043644429333037283",
    "fullText": "chase_thez https://t.co/xwtSsVKdD2",
    "publishTime": "2026-04-13T18:56:15"
  },
  {
    "user": {
      "screenName": "eric_kk97",
      "name": "ManFeed🍆"
    },
    "images": [
      "https://pbs.twimg.com/media/HFx72vBbcAAPd2n.jpg"
    ],
    "videos": [],
    "expandUrls": [],
    "tweetUrl": "https://x.com/eric_kk97/status/2043644515605774453",
    "fullText": "doyys https://t.co/mJ6ZGjFwVZ",
    "publishTime": "2026-04-13T18:56:36"
  },
  {
    "user": {
      "screenName": "eric_kk97",
      "name": "ManFeed🍆"
    },
    "images": [
      "https://pbs.twimg.com/media/HFyOKQybIAAcc7C.jpg"
    ],
    "videos": [],
    "expandUrls": [],
    "tweetUrl": "https://x.com/eric_kk97/status/2043664642690703747",
    "fullText": "dearnelson https://t.co/dmbQL2JPMB",
    "publishTime": "2026-04-13T20:16:34"
  },
  {
    "user": {
      "screenName": "Aninnjh",
      "name": "村长Anin"
    },
    "images": [
      "https://pbs.twimg.com/media/HFyTr3cboAAV435.jpg"
    ],
    "videos": [],
    "expandUrls": [],
    "tweetUrl": "https://x.com/Aninnjh/status/2043670724372795701",
    "fullText": "https://t.co/Y5ljjHEjLs",
    "publishTime": "2026-04-13T20:40:44"
  },
  {
    "user": {
      "screenName": "zdx1xx",
      "name": "犬黒"
    },
    "images": [],
    "videos": [],
    "expandUrls": [],
    "tweetUrl": "https://x.com/zdx1xx/status/2043670981898809576",
    "fullText": "感觉熊审美在开始退潮？\n是我的错觉么",
    "publishTime": "2026-04-13T20:41:46"
  },
  {
    "user": {
      "screenName": "huohuo0707330",
      "name": "嚯"
    },
    "images": [
      "https://pbs.twimg.com/media/HFyVWiPaoAAoB1P.jpg",
      "https://pbs.twimg.com/media/HFyVWiMbgAAUVhq.jpg"
    ],
    "videos": [],
    "expandUrls": [],
    "tweetUrl": "https://x.com/huohuo0707330/status/2043672616112894397",
    "fullText": "#上海 酒没啥劲儿啊  怎么大哥们都多了 https://t.co/HDnfuyfBaA",
    "publishTime": "2026-04-13T20:48:15"
  },
  {
    "user": {
      "screenName": "huohuo0707330",
      "name": "嚯"
    },
    "images": [],
    "videos": [],
    "expandUrls": [],
    "tweetUrl": "https://x.com/huohuo0707330/status/2043676111851413640",
    "fullText": "土老帽进城\n上海小精酿店酒好柔  感觉和上海人人不管好看与否都很精致一样  没有北京大部分超顶的酒精感  大家见面聊的都是项目\n还有就是为什么大周一  路边理发店都是女孩儿们在化妆  说得难听点都是站街n的妆容  太可怕了  以为是什么发廊",
    "publishTime": "2026-04-13T21:02:09"
  },
  {
    "user": {
      "screenName": "milk_leak",
      "name": "milk_leak"
    },
    "images": [
      "https://pbs.twimg.com/media/HFycM5Pa4AAY-iH.jpg",
      "https://pbs.twimg.com/media/HFycM5NbEAArDvI.jpg"
    ],
    "videos": [],
    "expandUrls": [],
    "tweetUrl": "https://x.com/milk_leak/status/2043680085463683233",
    "fullText": "翻开包皮试图显大 https://t.co/N3c6u5N00M",
    "publishTime": "2026-04-13T21:17:56"
  },
  {
    "user": {
      "screenName": "josephmrkao",
      "name": "185 Joseph"
    },
    "images": [],
    "videos": [
      "https://video.twimg.com/amplify_video/2043626214360072192/vid/avc1/1080x1920/CBRfqf_CQ_aKuk9G.mp4?tag=21"
    ],
    "expandUrls": [
      "http://link.me/185joseph"
    ],
    "tweetUrl": "https://x.com/josephmrkao/status/2043691928257183963",
    "fullText": "這個視角…只屬於螢幕前的你 😗\nThis angle… is just for you...\nhttps://t.co/YLTFp8lau4   @zyboy_03 https://t.co/TEDz3BxwLk",
    "publishTime": "2026-04-13T22:05:00"
  },
  {
    "user": {
      "screenName": "Doraemonphoto",
      "name": "Doraemon"
    },
    "images": [
      "https://pbs.twimg.com/media/HFyoPiwbYAELkud.jpg"
    ],
    "videos": [],
    "expandUrls": [],
    "tweetUrl": "https://x.com/Doraemonphoto/status/2043693330375365041",
    "fullText": "新的体育生 https://t.co/OV9AHje6hA",
    "publishTime": "2026-04-13T22:10:34"
  },
  {
    "user": {
      "screenName": "liangqu111",
      "name": "Leo qu"
    },
    "images": [
      "https://pbs.twimg.com/media/HFy2ccZa8AA4w2o.jpg",
      "https://pbs.twimg.com/media/HFy2cdLagAApJfO.jpg"
    ],
    "videos": [],
    "expandUrls": [],
    "tweetUrl": "https://x.com/liangqu111/status/2043708955415937468",
    "fullText": "出一波闲置内裤，图一都35一条，红蓝尺码为M，黑白尺码为s，图二尺码均为M，黄紫单丁30一条，蕾丝和平角50一条，都包邮，买的多🉑便宜🩲🩲🩲 https://t.co/RQqYWLU42Y",
    "publishTime": "2026-04-13T23:12:39"
  },
  {
    "user": {
      "screenName": "MCdanbaifen",
      "name": "猛吃蛋白粉🐯"
    },
    "images": [
      "https://pbs.twimg.com/media/HFy9s1IaEAAKR7E.jpg",
      "https://pbs.twimg.com/media/HFy9s2zbkAAqhet.jpg",
      "https://pbs.twimg.com/media/HFy9s6FbgAIqVRG.jpg",
      "https://pbs.twimg.com/media/HFy9s1ZaEAACHad.jpg"
    ],
    "videos": [],
    "expandUrls": [],
    "tweetUrl": "https://x.com/MCdanbaifen/status/2043716928917938560",
    "fullText": "还差一点点，小肚子要消灭了 https://t.co/Fu0C13s2ns",
    "publishTime": "2026-04-13T23:44:20"
  }
]
